Workbook
Name IDs_Clientes_Validos: #REF!
Name IDs_Productos_Validos: #REF!
Name ListaClientes: #REF!
Name RangoHistorico: OFFSET(#REF!,0,0,COUNTA(#REF!),8)
Name SegmentaciónDeDatos_Cliente: #N/A
Name SegmentaciónDeDatos_Mes: #N/A
Name SegmentaciónDeDatos_Producto: #N/A

Sheet Resumen Ejecutivo
A1: Checkpoint — Modelo BI de Ventas
A3: Flujo documentado: ETL (M) → Modelo estrella → DAX → Estadística → Escenarios
A5: KPI | B5: Resultado | D5: Cobertura del modelo | E5: Estado
A6: Registros | B6: =COUNTA('Dataset Principal'!B2:B5001) -> 5000 | D6: ETL y código M | E6: Implementado
A7: Ventas totales | B7: =SUM('Dataset Principal'!I2:I5001) -> 6.3295482e+08 | D7: Modelo estrella 1:N | E7: Implementado
A8: Margen neto estimado | B8: =SUM('Dataset Principal'!K2:K5001) -> 1.8988645e+08 | D8: DAX con VAR/RETURN | E8: Implementado
A9: Margen neto % | B9: =B8/B7 -> 0.3 | D9: Estadística y escenarios | E9: Implementado
A12: Hallazgos
A13: Las ventas suman $632,95 millones en 5.000 operaciones.
A14: Con costo estimado en 70%, el margen neto modelado es 30% de ventas.
A15: La media supera la mediana, señal de operaciones grandes que elevan el promedio.
A16: El objetivo de $5 millones se calcula con el margen unitario base.
A18: Nota de implementación
A19: Flujo implementado: consulta Power Query, tablas en el Modelo de datos, relaciones 1:N, medidas DAX, reporte ToolPak, escenarios y Buscar objetivo.

Sheet Tbl_Dataset
A1: Fecha_Operacion | B1: ID_Transaccion | C1: Bultos | D1: Precio_Mayorista | E1: Impuesto_Interno | F1: ID_Cliente | G1: ID_Producto | H1: Mes_Operacion | I1: Venta_Total | J1: Costo_Estimado | K1: Margen_Neto
A2: 46252 | B2: TX-100000 | C2: 6 | D2: 3044 | E2: 0.04 | F2: 2 | G2: 1 | H2: 1/8/2026 00:00:00 | I2: 18994.56 | J2: 13296.192 | K2: 5698.368
A3: 46149 | B3: TX-100001 | C3: 5 | D3: 12534 | E3: 0.11 | F3: 4 | G3: 2 | H3: 1/5/2026 00:00:00 | I3: 69563.7 | J3: 48694.59 | K3: 20869.11
A4: 46075 | B4: TX-100002 | C4: 2 | D4: 10179 | E4: 0.15 | F4: 4 | G4: 3 | H4: 1/2/2026 00:00:00 | I4: 23411.7 | J4: 16388.19 | K4: 7023.51
A5: 46126 | B5: TX-100003 | C5: 9 | D5: 2075 | E5: 0.09 | F5: 4 | G5: 4 | H5: 1/4/2026 00:00:00 | I5: 20355.75 | J5: 14249.025 | K5: 6106.725
A6: 46185 | B6: TX-100004 | C6: 3 | D6: 25407 | E6: 0.08 | F6: 5 | G6: 5 | H6: 1/6/2026 00:00:00 | I6: 82318.68 | J6: 57623.076 | K6: 24695.604
A7: 46386 | B7: TX-100005 | C7: 8 | D7: 32401 | E7: 0.15 | F7: 2 | G7: 6 | H7: 1/12/2026 00:00:00 | I7: 298089.2 | J7: 208662.44 | K7: 89426.76
A8: 46336 | B8: TX-100006 | C8: 4 | D8: 33553 | E8: 0.06 | F8: 1 | G8: 5 | H8: 1/11/2026 00:00:00 | I8: 142264.72 | J8: 99585.304 | K8: 42679.416
A9: 46238 | B9: TX-100007 | C9: 6 | D9: 5774 | F9: 5 | G9: 5 | H9: 1/8/2026 00:00:00 | I9: 34644 | J9: 24250.8 | K9: 10393.2
A10: 46372 | B10: TX-100008 | C10: 11 | D10: 21789 | F10: 1 | G10: 6 | H10: 1/12/2026 00:00:00 | I10: 239679 | J10: 167775.3 | K10: 71903.7
A11: 46268 | B11: TX-100009 | C11: 1 | D11: 31120 | E11: 0.11 | F11: 5 | G11: 2 | H11: 1/9/2026 00:00:00 | I11: 34543.2 | J11: 24180.24 | K11: 10362.96
A12: 46168 | B12: TX-100010 | C12: 5 | D12: 18941 | F12: 5 | G12: 5 | H12: 1/5/2026 00:00:00 | I12: 94705 | J12: 66293.5 | K12: 28411.5
A13: 46280 | B13: TX-100011 | C13: 5 | D13: 6089 | E13: 0.03 | F13: 1 | G13: 7 | H13: 1/9/2026 00:00:00 | I13: 31358.35 | J13: 21950.845 | K13: 9407.505
A14: 46211 | B14: TX-100012 | C14: 8 | D14: 30535 | E14: 0.12 | F14: 4 | G14: 2 | H14: 1/7/2026 00:00:00 | I14: 273593.6 | J14: 191515.52 | K14: 82078.08
A15: 46278 | B15: TX-100013 | C15: 10 | D15: 25346 | E15: 0.05 | F15: 5 | G15: 1 | H15: 1/9/2026 00:00:00 | I15: 266133 | J15: 186293.1 | K15: 79839.9
A16: 46176 | B16: TX-100014 | C16: 4 | D16: 2299 | E16: 0.03 | F16: 2 | G16: 1 | H16: 1/6/2026 00:00:00 | I16: 9471.88 | J16: 6630.316 | K16: 2841.564
A17: 46301 | B17: TX-100015 | C17: 10 | D17: 3179 | F17: 5 | G17: 4 | H17: 1/10/2026 00:00:00 | I17: 31790 | J17: 22253 | K17: 9537
A18: 46095 | B18: TX-100016 | C18: 7 | D18: 16266 | E18: 0.12 | F18: 4 | G18: 3 | H18: 1/3/2026 00:00:00 | I18: 127525.44 | J18: 89267.808 | K18: 38257.632
A19: 46301 | B19: TX-100017 | C19: 3 | D19: 16742 | E19: 0.11 | F19: 5 | G19: 3 | H19: 1/10/2026 00:00:00 | I19: 55750.86 | J19: 39025.602 | K19: 16725.258
A20: 46061 | B20: TX-100018 | C20: 2 | D20: 13533 | E20: 0.14 | F20: 3 | G20: 8 | H20: 1/2/2026 00:00:00 | I20: 30855.24 | J20: 21598.668 | K20: 9256.572
A21: 46158 | B21: TX-100019 | C21: 1 | D21: 5105 | E21: 0.09 | F21: 3 | G21: 7 | H21: 1/5/2026 00:00:00 | I21: 5564.45 | J21: 3895.115 | K21: 1669.335
A22: 46132 | B22: TX-100020 | C22: 10 | D22: 16885 | E22: 0.06 | F22: 2 | G22: 1 | H22: 1/4/2026 00:00:00 | I22: 178981 | J22: 125286.7 | K22: 53694.3
A23: 46316 | B23: TX-100021 | C23: 1 | D23: 13092 | F23: 1 | G23: 1 | H23: 1/10/2026 00:00:00 | I23: 13092 | J23: 9164.4 | K23: 3927.6
A24: 46303 | B24: TX-100022 | C24: 10 | D24: 26368 | F24: 3 | G24: 8 | H24: 1/10/2026 00:00:00 | I24: 263680 | J24: 184576 | K24: 79104
A25: 46265 | B25: TX-100023 | C25: 10 | D25: 21385 | F25: 4 | G25: 4 | H25: 1/8/2026 00:00:00 | I25: 213850 | J25: 149695 | K25: 64155
A26: 46229 | B26: TX-100024 | C26: 5 | D26: 23388 | F26: 2 | G26: 3 | H26: 1/7/2026 00:00:00 | I26: 116940 | J26: 81858 | K26: 35082
A27: 46126 | B27: TX-100025 | C27: 12 | D27: 2582 | E27: 0.05 | F27: 1 | G27: 6 | H27: 1/4/2026 00:00:00 | I27: 32533.2 | J27: 22773.24 | K27: 9759.96
A28: 46086 | B28: TX-100026 | C28: 2 | D28: 13067 | F28: 2 | G28: 2 | H28: 1/3/2026 00:00:00 | I28: 26134 | J28: 18293.8 | K28: 7840.2
A29: 46135 | B29: TX-100027 | C29: 8 | D29: 23563 | F29: 4 | G29: 7 | H29: 1/4/2026 00:00:00 | I29: 188504 | J29: 131952.8 | K29: 56551.2
A30: 46291 | B30: TX-100028 | C30: 10 | D30: 24849 | E30: 0.15 | F30: 4 | G30: 8 | H30: 1/9/2026 00:00:00 | I30: 285763.5 | J30: 200034.45 | K30: 85729.05
A31: 46058 | B31: TX-100029 | C31: 11 | D31: 20283 | E31: 0.12 | F31: 2 | G31: 6 | H31: 1/2/2026 00:00:00 | I31: 249886.56 | J31: 174920.59 | K31: 74965.968
A32: 46077 | B32: TX-100030 | C32: 12 | D32: 17890 | E32: 0.09 | F32: 1 | G32: 4 | H32: 1/2/2026 00:00:00 | I32: 234001.2 | J32: 163800.84 | K32: 70200.36
A33: 46199 | B33: TX-100031 | C33: 4 | D33: 6009 | E33: 0.09 | F33: 4 | G33: 2 | H33: 1/6/2026 00:00:00 | I33: 26199.24 | J33: 18339.468 | K33: 7859.772
A34: 46344 | B34: TX-100032 | C34: 11 | D34: 23552 | E34: 0.04 | F34: 2 | G34: 1 | H34: 1/11/2026 00:00:00 | I34: 269434.88 | J34: 188604.42 | K34: 80830.464
A35: 46181 | B35: TX-100033 | C35: 4 | D35: 27730 | F35: 5 | G35: 4 | H35: 1/6/2026 00:00:00 | I35: 110920 | J35: 77644 | K35: 33276
A36: 46115 | B36: TX-100034 | C36: 6 | D36: 11824 | F36: 4 | G36: 2 | H36: 1/4/2026 00:00:00 | I36: 70944 | J36: 49660.8 | K36: 21283.2
A37: 46128 | B37: TX-100035 | C37: 4 | D37: 16635 | E37: 0.02 | F37: 3 | G37: 1 | H37: 1/4/2026 00:00:00 | I37: 67870.8 | J37: 47509.56 | K37: 20361.24
A38: 46365 | B38: TX-100036 | C38: 1 | D38: 24659 | E38: 0.1 | F38: 1 | G38: 3 | H38: 1/12/2026 00:00:00 | I38: 27124.9 | J38: 18987.43 | K38: 8137.47
A39: 46094 | B39: TX-100037 | C39: 1 | D39: 25492 | E39: 0.07 | F39: 3 | G39: 5 | H39: 1/3/2026 00:00:00 | I39: 27276.44 | J39: 19093.508 | K39: 8182.932
A40: 46381 | B40: TX-100038 | C40: 4 | D40: 15290 | E40: 0.05 | F40: 5 | G40: 8 | H40: 1/12/2026 00:00:00 | I40: 64218 | J40: 44952.6 | K40: 19265.4
A41: 46027 | B41: TX-100039 | C41: 11 | D41: 24265 | E41: 0.14 | F41: 2 | G41: 1 | H41: 1/1/2026 00:00:00 | I41: 304283.1 | J41: 212998.17 | K41: 91284.93
A42: 46033 | B42: TX-100040 | C42: 8 | D42: 23440 | E42: 0.12 | F42: 4 | G42: 6 | H42: 1/1/2026 00:00:00 | I42: 210022.4 | J42: 147015.68 | K42: 63006.72
A43: 46169 | B43: TX-100041 | C43: 9 | D43: 17850 | F43: 3 | G43: 6 | H43: 1/5/2026 00:00:00 | I43: 160650 | J43: 112455 | K43: 48195
A44: 46199 | B44: TX-100042 | C44: 1 | D44: 7951 | E44: 0.05 | F44: 5 | G44: 5 | H44: 1/6/2026 00:00:00 | I44: 8348.55 | J44: 5843.985 | K44: 2504.565
A45: 46368 | B45: TX-100043 | C45: 11 | D45: 2916 | E45: 0.11 | F45: 1 | G45: 8 | H45: 1/12/2026 00:00:00 | I45: 35604.36 | J45: 24923.052 | K45: 10681.308
A46: 46332 | B46: TX-100044 | C46: 1 | D46: 15047 | F46: 5 | G46: 4 | H46: 1/11/2026 00:00:00 | I46: 15047 | J46: 10532.9 | K46: 4514.1
A47: 46201 | B47: TX-100045 | C47: 7 | D47: 6290 | E47: 0.06 | F47: 1 | G47: 1 | H47: 1/6/2026 00:00:00 | I47: 46671.8 | J47: 32670.26 | K47: 14001.54
A48: 46077 | B48: TX-100046 | C48: 2 | D48: 30335 | E48: 0.06 | F48: 2 | G48: 2 | H48: 1/2/2026 00:00:00 | I48: 64310.2 | J48: 45017.14 | K48: 19293.06
A49: 46305 | B49: TX-100047 | C49: 10 | D49: 11731 | E49: 0.02 | F49: 1 | G49: 7 | H49: 1/10/2026 00:00:00 | I49: 119656.2 | J49: 83759.34 | K49: 35896.86
A50: 46042 | B50: TX-100048 | C50: 9 | D50: 23322 | E50: 0.13 | F50: 4 | G50: 3 | H50: 1/1/2026 00:00:00 | I50: 237184.74 | J50: 166029.32 | K50: 71155.422
A51: 46345 | B51: TX-100049 | C51: 5 | D51: 22484 | E51: 0.03 | F51: 3 | G51: 3 | H51: 1/11/2026 00:00:00 | I51: 115792.6 | J51: 81054.82 | K51: 34737.78
A52: 46059 | B52: TX-100050 | C52: 7 | D52: 6756 | E52: 0.06 | F52: 5 | G52: 6 | H52: 1/2/2026 00:00:00 | I52: 50129.52 | J52: 35090.664 | K52: 15038.856
A53: 46162 | B53: TX-100051 | C53: 8 | D53: 27564 | E53: 0.03 | F53: 2 | G53: 3 | H53: 1/5/2026 00:00:00 | I53: 227127.36 | J53: 158989.15 | K53: 68138.208
A54: 46038 | B54: TX-100052 | C54: 8 | D54: 13613 | E54: 0.06 | F54: 2 | G54: 8 | H54: 1/1/2026 00:00:00 | I54: 115438.24 | J54: 80806.768 | K54: 34631.472
A55: 46228 | B55: TX-100053 | C55: 8 | D55: 14079 | E55: 0.03 | F55: 3 | G55: 5 | H55: 1/7/2026 00:00:00 | I55: 116010.96 | J55: 81207.672 | K55: 34803.288
A56: 46132 | B56: TX-100054 | C56: 3 | D56: 2565 | E56: 0.03 | F56: 5 | G56: 1 | H56: 1/4/2026 00:00:00 | I56: 7925.85 | J56: 5548.095 | K56: 2377.755
A57: 46375 | B57: TX-100055 | C57: 9 | D57: 25570 | E57: 0.07 | F57: 4 | G57: 2 | H57: 1/12/2026 00:00:00 | I57: 246239.1 | J57: 172367.37 | K57: 73871.73
A58: 46137 | B58: TX-100056 | C58: 2 | D58: 19591 | E58: 0.08 | F58: 5 | G58: 2 | H58: 1/4/2026 00:00:00 | I58: 42316.56 | J58: 29621.592 | K58: 12694.968
A59: 46189 | B59: TX-100057 | C59: 12 | D59: 13131 | E59: 0.04 | F59: 4 | G59: 4 | H59: 1/6/2026 00:00:00 | I59: 163874.88 | J59: 114712.42 | K59: 49162.464
A60: 46041 | B60: TX-100058 | C60: 6 | D60: 4864 | F60: 1 | G60: 5 | H60: 1/1/2026 00:00:00 | I60: 29184 | J60: 20428.8 | K60: 8755.2
A61: 46054 | B61: TX-100059 | C61: 2 | D61: 31799 | E61: 0.12 | F61: 1 | G61: 6 | H61: 1/2/2026 00:00:00 | I61: 71229.76 | J61: 49860.832 | K61: 21368.928
A62: 46154 | B62: TX-100060 | C62: 9 | D62: 13323 | E62: 0.14 | F62: 4 | G62: 6 | H62: 1/5/2026 00:00:00 | I62: 136693.98 | J62: 95685.786 | K62: 41008.194
A63: 46186 | B63: TX-100061 | C63: 9 | D63: 7187 | E63: 0.04 | F63: 1 | G63: 1 | H63: 1/6/2026 00:00:00 | I63: 67270.32 | J63: 47089.224 | K63: 20181.096
A64: 46093 | B64: TX-100062 | C64: 1 | D64: 13700 | E64: 0.12 | F64: 2 | G64: 1 | H64: 1/3/2026 00:00:00 | I64: 15344 | J64: 10740.8 | K64: 4603.2
A65: 46032 | B65: TX-100063 | C65: 6 | D65: 34511 | E65: 0.13 | F65: 5 | G65: 2 | H65: 1/1/2026 00:00:00 | I65: 233984.58 | J65: 163789.21 | K65: 70195.374
A66: 46317 | B66: TX-100064 | C66: 8 | D66: 24520 | F66: 2 | G66: 7 | H66: 1/10/2026 00:00:00 | I66: 196160 | J66: 137312 | K66: 58848
A67: 46158 | B67: TX-100065 | C67: 9 | D67: 22712 | E67: 0.14 | F67: 2 | G67: 5 | H67: 1/5/2026 00:00:00 | I67: 233025.12 | J67: 163117.58 | K67: 69907.536
A68: 46279 | B68: TX-100066 | C68: 10 | D68: 11180 | E68: 0.04 | F68: 5 | G68: 8 | H68: 1/9/2026 00:00:00 | I68: 116272 | J68: 81390.4 | K68: 34881.6
A69: 46027 | B69: TX-100067 | C69: 1 | D69: 28592 | F69: 5 | G69: 7 | H69: 1/1/2026 00:00:00 | I69: 28592 | J69: 20014.4 | K69: 8577.6
A70: 46037 | B70: TX-100068 | C70: 5 | D70: 7362 | E70: 0.12 | F70: 1 | G70: 8 | H70: 1/1/2026 00:00:00 | I70: 41227.2 | J70: 28859.04 | K70: 12368.16
A71: 46240 | B71: TX-100069 | C71: 3 | D71: 22050 | F71: 5 | G71: 1 | H71: 1/8/2026 00:00:00 | I71: 66150 | J71: 46305 | K71: 19845
B72: TX-100070 | C72: 11 | D72: 20250 | E72: 0.08 | F72: 1 | G72: 2 | I72: 240570 | J72: 168399 | K72: 72171
A73: 46252 | B73: TX-100071 | C73: 8 | D73: 5166 | E73: 0.11 | F73: 5 | G73: 8 | H73: 1/8/2026 00:00:00 | I73: 45874.08 | J73: 32111.856 | K73: 13762.224
A74: 46149 | B74: TX-100072 | C74: 8 | D74: 30089 | E74: 0.14 | F74: 2 | G74: 7 | H74: 1/5/2026 00:00:00 | I74: 274411.68 | J74: 192088.18 | K74: 82323.504
A75: 46075 | B75: TX-100073 | C75: 12 | D75: 34013 | E75: 0.09 | F75: 3 | G75: 1 | H75: 1/2/2026 00:00:00 | I75: 444890.04 | J75: 311423.03 | K75: 133467.01
A76: 46126 | B76: TX-100074 | C76: 12 | D76: 7791 | F76: 1 | G76: 1 | H76: 1/4/2026 00:00:00 | I76: 93492 | J76: 65444.4 | K76: 28047.6
A77: 46185 | B77: TX-100075 | C77: 3 | D77: 32892 | E77: 0.05 | F77: 4 | G77: 8 | H77: 1/6/2026 00:00:00 | I77: 103609.8 | J77: 72526.86 | K77: 31082.94
A78: 46386 | B78: TX-100076 | C78: 9 | D78: 2755 | E78: 0.06 | F78: 1 | G78: 5 | H78: 1/12/2026 00:00:00 | I78: 26282.7 | J78: 18397.89 | K78: 7884.81
A79: 46336 | B79: TX-100077 | C79: 3 | D79: 19554 | E79: 0.03 | F79: 2 | G79: 5 | H79: 1/11/2026 00:00:00 | I79: 60421.86 | J79: 42295.302 | K79: 18126.558
A80: 46238 | B80: TX-100078 | C80: 6 | D80: 10928 | E80: 0.06 | F80: 4 | G80: 8 | H80: 1/8/2026 00:00:00 | I80: 69502.08 | J80: 48651.456 | K80: 20850.624
A81: 46372 | B81: TX-100079 | C81: 12 | D81: 18746 | E81: 0.14 | F81: 2 | G81: 3 | H81: 1/12/2026 00:00:00 | I81: 256445.28 | J81: 179511.7 | K81: 76933.584
A82: 46268 | B82: TX-100080 | C82: 11 | D82: 9676 | E82: 0.07 | F82: 3 | G82: 6 | H82: 1/9/2026 00:00:00 | I82: 113886.52 | J82: 79720.564 | K82: 34165.956
A83: 46168 | B83: TX-100081 | C83: 9 | D83: 11444 | E83: 0.1 | F83: 4 | G83: 4 | H83: 1/5/2026 00:00:00 | I83: 113295.6 | J83: 79306.92 | K83: 33988.68
A84: 46280 | B84: TX-100082 | C84: 5 | D84: 31605 | F84: 1 | G84: 3 | H84: 1/9/2026 00:00:00 | I84: 158025 | J84: 110617.5 | K84: 47407.5
A85: 46211 | B85: TX-100083 | C85: 2 | D85: 5874 | E85: 0.05 | F85: 1 | G85: 8 | H85: 1/7/2026 00:00:00 | I85: 12335.4 | J85: 8634.78 | K85: 3700.62
A86: 46278 | B86: TX-100084 | C86: 5 | D86: 13716 | E86: 0.15 | F86: 5 | G86: 6 | H86: 1/9/2026 00:00:00 | I86: 78867 | J86: 55206.9 | K86: 23660.1
A87: 46176 | B87: TX-100085 | C87: 3 | D87: 33135 | F87: 3 | G87: 2 | H87: 1/6/2026 00:00:00 | I87: 99405 | J87: 69583.5 | K87: 29821.5
A88: 46301 | B88: TX-100086 | C88: 6 | D88: 6400 | F88: 3 | G88: 8 | H88: 1/10/2026 00:00:00 | I88: 38400 | J88: 26880 | K88: 11520
A89: 46095 | B89: TX-100087 | C89: 7 | D89: 10288 | F89: 3 | G89: 8 | H89: 1/3/2026 00:00:00 | I89: 72016 | J89: 50411.2 | K89: 21604.8
A90: 46301 | B90: TX-100088 | C90: 6 | D90: 10715 | E90: 0.07 | F90: 5 | G90: 6 | H90: 1/10/2026 00:00:00 | I90: 68790.3 | J90: 48153.21 | K90: 20637.09
A91: 46061 | B91: TX-100089 | C91: 10 | D91: 5065 | E91: 0.12 | F91: 4 | G91: 4 | H91: 1/2/2026 00:00:00 | I91: 56728 | J91: 39709.6 | K91: 17018.4
A92: 46158 | B92: TX-100090 | C92: 11 | D92: 24659 | E92: 0.04 | F92: 4 | G92: 1 | H92: 1/5/2026 00:00:00 | I92: 282098.96 | J92: 197469.27 | K92: 84629.688
A93: 46132 | B93: TX-100091 | C93: 10 | D93: 25538 | F93: 2 | G93: 3 | H93: 1/4/2026 00:00:00 | I93: 255380 | J93: 178766 | K93: 76614
A94: 46316 | B94: TX-100092 | C94: 12 | D94: 7030 | E94: 0.15 | F94: 4 | G94: 8 | H94: 1/10/2026 00:00:00 | I94: 97014 | J94: 67909.8 | K94: 29104.2
A95: 46303 | B95: TX-100093 | C95: 12 | D95: 5310 | F95: 1 | G95: 6 | H95: 1/10/2026 00:00:00 | I95: 63720 | J95: 44604 | K95: 19116
A96: 46265 | B96: TX-100094 | C96: 5 | D96: 26630 | F96: 3 | G96: 7 | H96: 1/8/2026 00:00:00 | I96: 133150 | J96: 93205 | K96: 39945
A97: 46229 | B97: TX-100095 | C97: 11 | D97: 3634 | E97: 0.07 | F97: 2 | G97: 4 | H97: 1/7/2026 00:00:00 | I97: 42772.18 | J97: 29940.526 | K97: 12831.654
A98: 46126 | B98: TX-100096 | C98: 3 | D98: 1899 | E98: 0.11 | F98: 4 | G98: 7 | H98: 1/4/2026 00:00:00 | I98: 6323.67 | J98: 4426.569 | K98: 1897.101
A99: 46086 | B99: TX-100097 | C99: 3 | D99: 32930 | E99: 0.1 | F99: 4 | G99: 7 | H99: 1/3/2026 00:00:00 | I99: 108669 | J99: 76068.3 | K99: 32600.7
A100: 46135 | B100: TX-100098 | C100: 2 | D100: 22114 | E100: 0.02 | F100: 1 | G100: 3 | H100: 1/4/2026 00:00:00 | I100: 45112.56 | J100: 31578.792 | K100: 13533.768
...

Sheet ToolPak Estadística
A1: Columna1
A3: Media | B3: 126590.96
A4: Error típico | B4: 1414.1501
A5: Mediana | B5: 99448.12
A6: Moda | B6: 31790
A7: Desviación estándar | B7: 99995.514
A8: Varianza de la muestra | B8: 9.9991027e+09
A9: Curtosis | B9: 0.075501368
A10: Coeficiente de asimetría | B10: 0.90954954
A11: Rango | B11: 472735
A12: Mínimo | B12: 1619
A13: Máximo | B13: 474354
A14: Suma | B14: 6.3295482e+08
A15: Cuenta | B15: 5000

Sheet Dataset Principal
A1: Fecha_Operacion | B1: ID_Transaccion | C1: Bultos | D1: Precio_Mayorista | E1: Impuesto_Interno | F1: ID_Cliente | G1: ID_Producto | H1: Mes_Operacion | I1: Venta_Total | J1: Costo_Estimado | K1: Margen_Neto
A2: 46252 | B2: TX-100000 | C2: 6 | D2: 3044 | E2: 0.04 | F2: 2 | G2: 1 | H2: =DATE(YEAR($A2),MONTH($A2),1) -> 46235 | I2: =$C2*$D2*(1+$E2) -> 18994.56 | J2: =I2*70% -> 13296.192 | K2: =I2-J2 -> 5698.368
A3: 46149 | B3: TX-100001 | C3: 5 | D3: 12534 | E3: 0.11 | F3: 4 | G3: 2 | H3: =DATE(YEAR($A3),MONTH($A3),1) -> 46143 | I3: =$C3*$D3*(1+$E3) -> 69563.7 | J3: =I3*70% -> 48694.59 | K3: =I3-J3 -> 20869.11
A4: 46075 | B4: TX-100002 | C4: 2 | D4: 10179 | E4: 0.15 | F4: 4 | G4: 3 | H4: =DATE(YEAR($A4),MONTH($A4),1) -> 46054 | I4: =$C4*$D4*(1+$E4) -> 23411.7 | J4: =I4*70% -> 16388.19 | K4: =I4-J4 -> 7023.51
A5: 46126 | B5: TX-100003 | C5: 9 | D5: 2075 | E5: 0.09 | F5: 4 | G5: 4 | H5: =DATE(YEAR($A5),MONTH($A5),1) -> 46113 | I5: =$C5*$D5*(1+$E5) -> 20355.75 | J5: =I5*70% -> 14249.025 | K5: =I5-J5 -> 6106.725
A6: 46185 | B6: TX-100004 | C6: 3 | D6: 25407 | E6: 0.08 | F6: 5 | G6: 5 | H6: =DATE(YEAR($A6),MONTH($A6),1) -> 46174 | I6: =$C6*$D6*(1+$E6) -> 82318.68 | J6: =I6*70% -> 57623.076 | K6: =I6-J6 -> 24695.604
A7: 46386 | B7: TX-100005 | C7: 8 | D7: 32401 | E7: 0.15 | F7: 2 | G7: 6 | H7: =DATE(YEAR($A7),MONTH($A7),1) -> 46357 | I7: =$C7*$D7*(1+$E7) -> 298089.2 | J7: =I7*70% -> 208662.44 | K7: =I7-J7 -> 89426.76
A8: 46336 | B8: TX-100006 | C8: 4 | D8: 33553 | E8: 0.06 | F8: 1 | G8: 5 | H8: =DATE(YEAR($A8),MONTH($A8),1) -> 46327 | I8: =$C8*$D8*(1+$E8) -> 142264.72 | J8: =I8*70% -> 99585.304 | K8: =I8-J8 -> 42679.416
A9: 46238 | B9: TX-100007 | C9: 6 | D9: 5774 | F9: 5 | G9: 5 | H9: =DATE(YEAR($A9),MONTH($A9),1) -> 46235 | I9: =$C9*$D9*(1+$E9) -> 34644 | J9: =I9*70% -> 24250.8 | K9: =I9-J9 -> 10393.2
A10: 46372 | B10: TX-100008 | C10: 11 | D10: 21789 | F10: 1 | G10: 6 | H10: =DATE(YEAR($A10),MONTH($A10),1) -> 46357 | I10: =$C10*$D10*(1+$E10) -> 239679 | J10: =I10*70% -> 167775.3 | K10: =I10-J10 -> 71903.7
A11: 46268 | B11: TX-100009 | C11: 1 | D11: 31120 | E11: 0.11 | F11: 5 | G11: 2 | H11: =DATE(YEAR($A11),MONTH($A11),1) -> 46266 | I11: =$C11*$D11*(1+$E11) -> 34543.2 | J11: =I11*70% -> 24180.24 | K11: =I11-J11 -> 10362.96
A12: 46168 | B12: TX-100010 | C12: 5 | D12: 18941 | F12: 5 | G12: 5 | H12: =DATE(YEAR($A12),MONTH($A12),1) -> 46143 | I12: =$C12*$D12*(1+$E12) -> 94705 | J12: =I12*70% -> 66293.5 | K12: =I12-J12 -> 28411.5
A13: 46280 | B13: TX-100011 | C13: 5 | D13: 6089 | E13: 0.03 | F13: 1 | G13: 7 | H13: =DATE(YEAR($A13),MONTH($A13),1) -> 46266 | I13: =$C13*$D13*(1+$E13) -> 31358.35 | J13: =I13*70% -> 21950.845 | K13: =I13-J13 -> 9407.505
A14: 46211 | B14: TX-100012 | C14: 8 | D14: 30535 | E14: 0.12 | F14: 4 | G14: 2 | H14: =DATE(YEAR($A14),MONTH($A14),1) -> 46204 | I14: =$C14*$D14*(1+$E14) -> 273593.6 | J14: =I14*70% -> 191515.52 | K14: =I14-J14 -> 82078.08
A15: 46278 | B15: TX-100013 | C15: 10 | D15: 25346 | E15: 0.05 | F15: 5 | G15: 1 | H15: =DATE(YEAR($A15),MONTH($A15),1) -> 46266 | I15: =$C15*$D15*(1+$E15) -> 266133 | J15: =I15*70% -> 186293.1 | K15: =I15-J15 -> 79839.9
A16: 46176 | B16: TX-100014 | C16: 4 | D16: 2299 | E16: 0.03 | F16: 2 | G16: 1 | H16: =DATE(YEAR($A16),MONTH($A16),1) -> 46174 | I16: =$C16*$D16*(1+$E16) -> 9471.88 | J16: =I16*70% -> 6630.316 | K16: =I16-J16 -> 2841.564
A17: 46301 | B17: TX-100015 | C17: 10 | D17: 3179 | F17: 5 | G17: 4 | H17: =DATE(YEAR($A17),MONTH($A17),1) -> 46296 | I17: =$C17*$D17*(1+$E17) -> 31790 | J17: =I17*70% -> 22253 | K17: =I17-J17 -> 9537
A18: 46095 | B18: TX-100016 | C18: 7 | D18: 16266 | E18: 0.12 | F18: 4 | G18: 3 | H18: =DATE(YEAR($A18),MONTH($A18),1) -> 46082 | I18: =$C18*$D18*(1+$E18) -> 127525.44 | J18: =I18*70% -> 89267.808 | K18: =I18-J18 -> 38257.632
A19: 46301 | B19: TX-100017 | C19: 3 | D19: 16742 | E19: 0.11 | F19: 5 | G19: 3 | H19: =DATE(YEAR($A19),MONTH($A19),1) -> 46296 | I19: =$C19*$D19*(1+$E19) -> 55750.86 | J19: =I19*70% -> 39025.602 | K19: =I19-J19 -> 16725.258
A20: 46061 | B20: TX-100018 | C20: 2 | D20: 13533 | E20: 0.14 | F20: 3 | G20: 8 | H20: =DATE(YEAR($A20),MONTH($A20),1) -> 46054 | I20: =$C20*$D20*(1+$E20) -> 30855.24 | J20: =I20*70% -> 21598.668 | K20: =I20-J20 -> 9256.572
A21: 46158 | B21: TX-100019 | C21: 1 | D21: 5105 | E21: 0.09 | F21: 3 | G21: 7 | H21: =DATE(YEAR($A21),MONTH($A21),1) -> 46143 | I21: =$C21*$D21*(1+$E21) -> 5564.45 | J21: =I21*70% -> 3895.115 | K21: =I21-J21 -> 1669.335
A22: 46132 | B22: TX-100020 | C22: 10 | D22: 16885 | E22: 0.06 | F22: 2 | G22: 1 | H22: =DATE(YEAR($A22),MONTH($A22),1) -> 46113 | I22: =$C22*$D22*(1+$E22) -> 178981 | J22: =I22*70% -> 125286.7 | K22: =I22-J22 -> 53694.3
A23: 46316 | B23: TX-100021 | C23: 1 | D23: 13092 | F23: 1 | G23: 1 | H23: =DATE(YEAR($A23),MONTH($A23),1) -> 46296 | I23: =$C23*$D23*(1+$E23) -> 13092 | J23: =I23*70% -> 9164.4 | K23: =I23-J23 -> 3927.6
A24: 46303 | B24: TX-100022 | C24: 10 | D24: 26368 | F24: 3 | G24: 8 | H24: =DATE(YEAR($A24),MONTH($A24),1) -> 46296 | I24: =$C24*$D24*(1+$E24) -> 263680 | J24: =I24*70% -> 184576 | K24: =I24-J24 -> 79104
A25: 46265 | B25: TX-100023 | C25: 10 | D25: 21385 | F25: 4 | G25: 4 | H25: =DATE(YEAR($A25),MONTH($A25),1) -> 46235 | I25: =$C25*$D25*(1+$E25) -> 213850 | J25: =I25*70% -> 149695 | K25: =I25-J25 -> 64155
A26: 46229 | B26: TX-100024 | C26: 5 | D26: 23388 | F26: 2 | G26: 3 | H26: =DATE(YEAR($A26),MONTH($A26),1) -> 46204 | I26: =$C26*$D26*(1+$E26) -> 116940 | J26: =I26*70% -> 81858 | K26: =I26-J26 -> 35082
A27: 46126 | B27: TX-100025 | C27: 12 | D27: 2582 | E27: 0.05 | F27: 1 | G27: 6 | H27: =DATE(YEAR($A27),MONTH($A27),1) -> 46113 | I27: =$C27*$D27*(1+$E27) -> 32533.2 | J27: =I27*70% -> 22773.24 | K27: =I27-J27 -> 9759.96
A28: 46086 | B28: TX-100026 | C28: 2 | D28: 13067 | F28: 2 | G28: 2 | H28: =DATE(YEAR($A28),MONTH($A28),1) -> 46082 | I28: =$C28*$D28*(1+$E28) -> 26134 | J28: =I28*70% -> 18293.8 | K28: =I28-J28 -> 7840.2
A29: 46135 | B29: TX-100027 | C29: 8 | D29: 23563 | F29: 4 | G29: 7 | H29: =DATE(YEAR($A29),MONTH($A29),1) -> 46113 | I29: =$C29*$D29*(1+$E29) -> 188504 | J29: =I29*70% -> 131952.8 | K29: =I29-J29 -> 56551.2
A30: 46291 | B30: TX-100028 | C30: 10 | D30: 24849 | E30: 0.15 | F30: 4 | G30: 8 | H30: =DATE(YEAR($A30),MONTH($A30),1) -> 46266 | I30: =$C30*$D30*(1+$E30) -> 285763.5 | J30: =I30*70% -> 200034.45 | K30: =I30-J30 -> 85729.05
A31: 46058 | B31: TX-100029 | C31: 11 | D31: 20283 | E31: 0.12 | F31: 2 | G31: 6 | H31: =DATE(YEAR($A31),MONTH($A31),1) -> 46054 | I31: =$C31*$D31*(1+$E31) -> 249886.56 | J31: =I31*70% -> 174920.59 | K31: =I31-J31 -> 74965.968
A32: 46077 | B32: TX-100030 | C32: 12 | D32: 17890 | E32: 0.09 | F32: 1 | G32: 4 | H32: =DATE(YEAR($A32),MONTH($A32),1) -> 46054 | I32: =$C32*$D32*(1+$E32) -> 234001.2 | J32: =I32*70% -> 163800.84 | K32: =I32-J32 -> 70200.36
A33: 46199 | B33: TX-100031 | C33: 4 | D33: 6009 | E33: 0.09 | F33: 4 | G33: 2 | H33: =DATE(YEAR($A33),MONTH($A33),1) -> 46174 | I33: =$C33*$D33*(1+$E33) -> 26199.24 | J33: =I33*70% -> 18339.468 | K33: =I33-J33 -> 7859.772
A34: 46344 | B34: TX-100032 | C34: 11 | D34: 23552 | E34: 0.04 | F34: 2 | G34: 1 | H34: =DATE(YEAR($A34),MONTH($A34),1) -> 46327 | I34: =$C34*$D34*(1+$E34) -> 269434.88 | J34: =I34*70% -> 188604.42 | K34: =I34-J34 -> 80830.464
A35: 46181 | B35: TX-100033 | C35: 4 | D35: 27730 | F35: 5 | G35: 4 | H35: =DATE(YEAR($A35),MONTH($A35),1) -> 46174 | I35: =$C35*$D35*(1+$E35) -> 110920 | J35: =I35*70% -> 77644 | K35: =I35-J35 -> 33276
A36: 46115 | B36: TX-100034 | C36: 6 | D36: 11824 | F36: 4 | G36: 2 | H36: =DATE(YEAR($A36),MONTH($A36),1) -> 46113 | I36: =$C36*$D36*(1+$E36) -> 70944 | J36: =I36*70% -> 49660.8 | K36: =I36-J36 -> 21283.2
A37: 46128 | B37: TX-100035 | C37: 4 | D37: 16635 | E37: 0.02 | F37: 3 | G37: 1 | H37: =DATE(YEAR($A37),MONTH($A37),1) -> 46113 | I37: =$C37*$D37*(1+$E37) -> 67870.8 | J37: =I37*70% -> 47509.56 | K37: =I37-J37 -> 20361.24
A38: 46365 | B38: TX-100036 | C38: 1 | D38: 24659 | E38: 0.1 | F38: 1 | G38: 3 | H38: =DATE(YEAR($A38),MONTH($A38),1) -> 46357 | I38: =$C38*$D38*(1+$E38) -> 27124.9 | J38: =I38*70% -> 18987.43 | K38: =I38-J38 -> 8137.47
A39: 46094 | B39: TX-100037 | C39: 1 | D39: 25492 | E39: 0.07 | F39: 3 | G39: 5 | H39: =DATE(YEAR($A39),MONTH($A39),1) -> 46082 | I39: =$C39*$D39*(1+$E39) -> 27276.44 | J39: =I39*70% -> 19093.508 | K39: =I39-J39 -> 8182.932
A40: 46381 | B40: TX-100038 | C40: 4 | D40: 15290 | E40: 0.05 | F40: 5 | G40: 8 | H40: =DATE(YEAR($A40),MONTH($A40),1) -> 46357 | I40: =$C40*$D40*(1+$E40) -> 64218 | J40: =I40*70% -> 44952.6 | K40: =I40-J40 -> 19265.4
A41: 46027 | B41: TX-100039 | C41: 11 | D41: 24265 | E41: 0.14 | F41: 2 | G41: 1 | H41: =DATE(YEAR($A41),MONTH($A41),1) -> 46023 | I41: =$C41*$D41*(1+$E41) -> 304283.1 | J41: =I41*70% -> 212998.17 | K41: =I41-J41 -> 91284.93
A42: 46033 | B42: TX-100040 | C42: 8 | D42: 23440 | E42: 0.12 | F42: 4 | G42: 6 | H42: =DATE(YEAR($A42),MONTH($A42),1) -> 46023 | I42: =$C42*$D42*(1+$E42) -> 210022.4 | J42: =I42*70% -> 147015.68 | K42: =I42-J42 -> 63006.72
A43: 46169 | B43: TX-100041 | C43: 9 | D43: 17850 | F43: 3 | G43: 6 | H43: =DATE(YEAR($A43),MONTH($A43),1) -> 46143 | I43: =$C43*$D43*(1+$E43) -> 160650 | J43: =I43*70% -> 112455 | K43: =I43-J43 -> 48195
A44: 46199 | B44: TX-100042 | C44: 1 | D44: 7951 | E44: 0.05 | F44: 5 | G44: 5 | H44: =DATE(YEAR($A44),MONTH($A44),1) -> 46174 | I44: =$C44*$D44*(1+$E44) -> 8348.55 | J44: =I44*70% -> 5843.985 | K44: =I44-J44 -> 2504.565
A45: 46368 | B45: TX-100043 | C45: 11 | D45: 2916 | E45: 0.11 | F45: 1 | G45: 8 | H45: =DATE(YEAR($A45),MONTH($A45),1) -> 46357 | I45: =$C45*$D45*(1+$E45) -> 35604.36 | J45: =I45*70% -> 24923.052 | K45: =I45-J45 -> 10681.308
A46: 46332 | B46: TX-100044 | C46: 1 | D46: 15047 | F46: 5 | G46: 4 | H46: =DATE(YEAR($A46),MONTH($A46),1) -> 46327 | I46: =$C46*$D46*(1+$E46) -> 15047 | J46: =I46*70% -> 10532.9 | K46: =I46-J46 -> 4514.1
A47: 46201 | B47: TX-100045 | C47: 7 | D47: 6290 | E47: 0.06 | F47: 1 | G47: 1 | H47: =DATE(YEAR($A47),MONTH($A47),1) -> 46174 | I47: =$C47*$D47*(1+$E47) -> 46671.8 | J47: =I47*70% -> 32670.26 | K47: =I47-J47 -> 14001.54
A48: 46077 | B48: TX-100046 | C48: 2 | D48: 30335 | E48: 0.06 | F48: 2 | G48: 2 | H48: =DATE(YEAR($A48),MONTH($A48),1) -> 46054 | I48: =$C48*$D48*(1+$E48) -> 64310.2 | J48: =I48*70% -> 45017.14 | K48: =I48-J48 -> 19293.06
A49: 46305 | B49: TX-100047 | C49: 10 | D49: 11731 | E49: 0.02 | F49: 1 | G49: 7 | H49: =DATE(YEAR($A49),MONTH($A49),1) -> 46296 | I49: =$C49*$D49*(1+$E49) -> 119656.2 | J49: =I49*70% -> 83759.34 | K49: =I49-J49 -> 35896.86
A50: 46042 | B50: TX-100048 | C50: 9 | D50: 23322 | E50: 0.13 | F50: 4 | G50: 3 | H50: =DATE(YEAR($A50),MONTH($A50),1) -> 46023 | I50: =$C50*$D50*(1+$E50) -> 237184.74 | J50: =I50*70% -> 166029.32 | K50: =I50-J50 -> 71155.422
A51: 46345 | B51: TX-100049 | C51: 5 | D51: 22484 | E51: 0.03 | F51: 3 | G51: 3 | H51: =DATE(YEAR($A51),MONTH($A51),1) -> 46327 | I51: =$C51*$D51*(1+$E51) -> 115792.6 | J51: =I51*70% -> 81054.82 | K51: =I51-J51 -> 34737.78
A52: 46059 | B52: TX-100050 | C52: 7 | D52: 6756 | E52: 0.06 | F52: 5 | G52: 6 | H52: =DATE(YEAR($A52),MONTH($A52),1) -> 46054 | I52: =$C52*$D52*(1+$E52) -> 50129.52 | J52: =I52*70% -> 35090.664 | K52: =I52-J52 -> 15038.856
A53: 46162 | B53: TX-100051 | C53: 8 | D53: 27564 | E53: 0.03 | F53: 2 | G53: 3 | H53: =DATE(YEAR($A53),MONTH($A53),1) -> 46143 | I53: =$C53*$D53*(1+$E53) -> 227127.36 | J53: =I53*70% -> 158989.15 | K53: =I53-J53 -> 68138.208
A54: 46038 | B54: TX-100052 | C54: 8 | D54: 13613 | E54: 0.06 | F54: 2 | G54: 8 | H54: =DATE(YEAR($A54),MONTH($A54),1) -> 46023 | I54: =$C54*$D54*(1+$E54) -> 115438.24 | J54: =I54*70% -> 80806.768 | K54: =I54-J54 -> 34631.472
A55: 46228 | B55: TX-100053 | C55: 8 | D55: 14079 | E55: 0.03 | F55: 3 | G55: 5 | H55: =DATE(YEAR($A55),MONTH($A55),1) -> 46204 | I55: =$C55*$D55*(1+$E55) -> 116010.96 | J55: =I55*70% -> 81207.672 | K55: =I55-J55 -> 34803.288
A56: 46132 | B56: TX-100054 | C56: 3 | D56: 2565 | E56: 0.03 | F56: 5 | G56: 1 | H56: =DATE(YEAR($A56),MONTH($A56),1) -> 46113 | I56: =$C56*$D56*(1+$E56) -> 7925.85 | J56: =I56*70% -> 5548.095 | K56: =I56-J56 -> 2377.755
A57: 46375 | B57: TX-100055 | C57: 9 | D57: 25570 | E57: 0.07 | F57: 4 | G57: 2 | H57: =DATE(YEAR($A57),MONTH($A57),1) -> 46357 | I57: =$C57*$D57*(1+$E57) -> 246239.1 | J57: =I57*70% -> 172367.37 | K57: =I57-J57 -> 73871.73
A58: 46137 | B58: TX-100056 | C58: 2 | D58: 19591 | E58: 0.08 | F58: 5 | G58: 2 | H58: =DATE(YEAR($A58),MONTH($A58),1) -> 46113 | I58: =$C58*$D58*(1+$E58) -> 42316.56 | J58: =I58*70% -> 29621.592 | K58: =I58-J58 -> 12694.968
A59: 46189 | B59: TX-100057 | C59: 12 | D59: 13131 | E59: 0.04 | F59: 4 | G59: 4 | H59: =DATE(YEAR($A59),MONTH($A59),1) -> 46174 | I59: =$C59*$D59*(1+$E59) -> 163874.88 | J59: =I59*70% -> 114712.42 | K59: =I59-J59 -> 49162.464
A60: 46041 | B60: TX-100058 | C60: 6 | D60: 4864 | F60: 1 | G60: 5 | H60: =DATE(YEAR($A60),MONTH($A60),1) -> 46023 | I60: =$C60*$D60*(1+$E60) -> 29184 | J60: =I60*70% -> 20428.8 | K60: =I60-J60 -> 8755.2
A61: 46054 | B61: TX-100059 | C61: 2 | D61: 31799 | E61: 0.12 | F61: 1 | G61: 6 | H61: =DATE(YEAR($A61),MONTH($A61),1) -> 46054 | I61: =$C61*$D61*(1+$E61) -> 71229.76 | J61: =I61*70% -> 49860.832 | K61: =I61-J61 -> 21368.928
A62: 46154 | B62: TX-100060 | C62: 9 | D62: 13323 | E62: 0.14 | F62: 4 | G62: 6 | H62: =DATE(YEAR($A62),MONTH($A62),1) -> 46143 | I62: =$C62*$D62*(1+$E62) -> 136693.98 | J62: =I62*70% -> 95685.786 | K62: =I62-J62 -> 41008.194
A63: 46186 | B63: TX-100061 | C63: 9 | D63: 7187 | E63: 0.04 | F63: 1 | G63: 1 | H63: =DATE(YEAR($A63),MONTH($A63),1) -> 46174 | I63: =$C63*$D63*(1+$E63) -> 67270.32 | J63: =I63*70% -> 47089.224 | K63: =I63-J63 -> 20181.096
A64: 46093 | B64: TX-100062 | C64: 1 | D64: 13700 | E64: 0.12 | F64: 2 | G64: 1 | H64: =DATE(YEAR($A64),MONTH($A64),1) -> 46082 | I64: =$C64*$D64*(1+$E64) -> 15344 | J64: =I64*70% -> 10740.8 | K64: =I64-J64 -> 4603.2
A65: 46032 | B65: TX-100063 | C65: 6 | D65: 34511 | E65: 0.13 | F65: 5 | G65: 2 | H65: =DATE(YEAR($A65),MONTH($A65),1) -> 46023 | I65: =$C65*$D65*(1+$E65) -> 233984.58 | J65: =I65*70% -> 163789.21 | K65: =I65-J65 -> 70195.374
A66: 46317 | B66: TX-100064 | C66: 8 | D66: 24520 | F66: 2 | G66: 7 | H66: =DATE(YEAR($A66),MONTH($A66),1) -> 46296 | I66: =$C66*$D66*(1+$E66) -> 196160 | J66: =I66*70% -> 137312 | K66: =I66-J66 -> 58848
A67: 46158 | B67: TX-100065 | C67: 9 | D67: 22712 | E67: 0.14 | F67: 2 | G67: 5 | H67: =DATE(YEAR($A67),MONTH($A67),1) -> 46143 | I67: =$C67*$D67*(1+$E67) -> 233025.12 | J67: =I67*70% -> 163117.58 | K67: =I67-J67 -> 69907.536
A68: 46279 | B68: TX-100066 | C68: 10 | D68: 11180 | E68: 0.04 | F68: 5 | G68: 8 | H68: =DATE(YEAR($A68),MONTH($A68),1) -> 46266 | I68: =$C68*$D68*(1+$E68) -> 116272 | J68: =I68*70% -> 81390.4 | K68: =I68-J68 -> 34881.6
A69: 46027 | B69: TX-100067 | C69: 1 | D69: 28592 | F69: 5 | G69: 7 | H69: =DATE(YEAR($A69),MONTH($A69),1) -> 46023 | I69: =$C69*$D69*(1+$E69) -> 28592 | J69: =I69*70% -> 20014.4 | K69: =I69-J69 -> 8577.6
A70: 46037 | B70: TX-100068 | C70: 5 | D70: 7362 | E70: 0.12 | F70: 1 | G70: 8 | H70: =DATE(YEAR($A70),MONTH($A70),1) -> 46023 | I70: =$C70*$D70*(1+$E70) -> 41227.2 | J70: =I70*70% -> 28859.04 | K70: =I70-J70 -> 12368.16
A71: 46240 | B71: TX-100069 | C71: 3 | D71: 22050 | F71: 5 | G71: 1 | H71: =DATE(YEAR($A71),MONTH($A71),1) -> 46235 | I71: =$C71*$D71*(1+$E71) -> 66150 | J71: =I71*70% -> 46305 | K71: =I71-J71 -> 19845
A72: Fecha_Operacion | B72: TX-100070 | C72: 11 | D72: 20250 | E72: 0.08 | F72: 1 | G72: 2 | H72: =DATE(YEAR($A72),MONTH($A72),1) -> #VALUE! | I72: =$C72*$D72*(1+$E72) -> 240570 | J72: =I72*70% -> 168399 | K72: =I72-J72 -> 72171
A73: 46252 | B73: TX-100071 | C73: 8 | D73: 5166 | E73: 0.11 | F73: 5 | G73: 8 | H73: =DATE(YEAR($A73),MONTH($A73),1) -> 46235 | I73: =$C73*$D73*(1+$E73) -> 45874.08 | J73: =I73*70% -> 32111.856 | K73: =I73-J73 -> 13762.224
A74: 46149 | B74: TX-100072 | C74: 8 | D74: 30089 | E74: 0.14 | F74: 2 | G74: 7 | H74: =DATE(YEAR($A74),MONTH($A74),1) -> 46143 | I74: =$C74*$D74*(1+$E74) -> 274411.68 | J74: =I74*70% -> 192088.18 | K74: =I74-J74 -> 82323.504
A75: 46075 | B75: TX-100073 | C75: 12 | D75: 34013 | E75: 0.09 | F75: 3 | G75: 1 | H75: =DATE(YEAR($A75),MONTH($A75),1) -> 46054 | I75: =$C75*$D75*(1+$E75) -> 444890.04 | J75: =I75*70% -> 311423.03 | K75: =I75-J75 -> 133467.01
A76: 46126 | B76: TX-100074 | C76: 12 | D76: 7791 | F76: 1 | G76: 1 | H76: =DATE(YEAR($A76),MONTH($A76),1) -> 46113 | I76: =$C76*$D76*(1+$E76) -> 93492 | J76: =I76*70% -> 65444.4 | K76: =I76-J76 -> 28047.6
A77: 46185 | B77: TX-100075 | C77: 3 | D77: 32892 | E77: 0.05 | F77: 4 | G77: 8 | H77: =DATE(YEAR($A77),MONTH($A77),1) -> 46174 | I77: =$C77*$D77*(1+$E77) -> 103609.8 | J77: =I77*70% -> 72526.86 | K77: =I77-J77 -> 31082.94
A78: 46386 | B78: TX-100076 | C78: 9 | D78: 2755 | E78: 0.06 | F78: 1 | G78: 5 | H78: =DATE(YEAR($A78),MONTH($A78),1) -> 46357 | I78: =$C78*$D78*(1+$E78) -> 26282.7 | J78: =I78*70% -> 18397.89 | K78: =I78-J78 -> 7884.81
A79: 46336 | B79: TX-100077 | C79: 3 | D79: 19554 | E79: 0.03 | F79: 2 | G79: 5 | H79: =DATE(YEAR($A79),MONTH($A79),1) -> 46327 | I79: =$C79*$D79*(1+$E79) -> 60421.86 | J79: =I79*70% -> 42295.302 | K79: =I79-J79 -> 18126.558
A80: 46238 | B80: TX-100078 | C80: 6 | D80: 10928 | E80: 0.06 | F80: 4 | G80: 8 | H80: =DATE(YEAR($A80),MONTH($A80),1) -> 46235 | I80: =$C80*$D80*(1+$E80) -> 69502.08 | J80: =I80*70% -> 48651.456 | K80: =I80-J80 -> 20850.624
A81: 46372 | B81: TX-100079 | C81: 12 | D81: 18746 | E81: 0.14 | F81: 2 | G81: 3 | H81: =DATE(YEAR($A81),MONTH($A81),1) -> 46357 | I81: =$C81*$D81*(1+$E81) -> 256445.28 | J81: =I81*70% -> 179511.7 | K81: =I81-J81 -> 76933.584
A82: 46268 | B82: TX-100080 | C82: 11 | D82: 9676 | E82: 0.07 | F82: 3 | G82: 6 | H82: =DATE(YEAR($A82),MONTH($A82),1) -> 46266 | I82: =$C82*$D82*(1+$E82) -> 113886.52 | J82: =I82*70% -> 79720.564 | K82: =I82-J82 -> 34165.956
A83: 46168 | B83: TX-100081 | C83: 9 | D83: 11444 | E83: 0.1 | F83: 4 | G83: 4 | H83: =DATE(YEAR($A83),MONTH($A83),1) -> 46143 | I83: =$C83*$D83*(1+$E83) -> 113295.6 | J83: =I83*70% -> 79306.92 | K83: =I83-J83 -> 33988.68
A84: 46280 | B84: TX-100082 | C84: 5 | D84: 31605 | F84: 1 | G84: 3 | H84: =DATE(YEAR($A84),MONTH($A84),1) -> 46266 | I84: =$C84*$D84*(1+$E84) -> 158025 | J84: =I84*70% -> 110617.5 | K84: =I84-J84 -> 47407.5
A85: 46211 | B85: TX-100083 | C85: 2 | D85: 5874 | E85: 0.05 | F85: 1 | G85: 8 | H85: =DATE(YEAR($A85),MONTH($A85),1) -> 46204 | I85: =$C85*$D85*(1+$E85) -> 12335.4 | J85: =I85*70% -> 8634.78 | K85: =I85-J85 -> 3700.62
A86: 46278 | B86: TX-100084 | C86: 5 | D86: 13716 | E86: 0.15 | F86: 5 | G86: 6 | H86: =DATE(YEAR($A86),MONTH($A86),1) -> 46266 | I86: =$C86*$D86*(1+$E86) -> 78867 | J86: =I86*70% -> 55206.9 | K86: =I86-J86 -> 23660.1
A87: 46176 | B87: TX-100085 | C87: 3 | D87: 33135 | F87: 3 | G87: 2 | H87: =DATE(YEAR($A87),MONTH($A87),1) -> 46174 | I87: =$C87*$D87*(1+$E87) -> 99405 | J87: =I87*70% -> 69583.5 | K87: =I87-J87 -> 29821.5
A88: 46301 | B88: TX-100086 | C88: 6 | D88: 6400 | F88: 3 | G88: 8 | H88: =DATE(YEAR($A88),MONTH($A88),1) -> 46296 | I88: =$C88*$D88*(1+$E88) -> 38400 | J88: =I88*70% -> 26880 | K88: =I88-J88 -> 11520
A89: 46095 | B89: TX-100087 | C89: 7 | D89: 10288 | F89: 3 | G89: 8 | H89: =DATE(YEAR($A89),MONTH($A89),1) -> 46082 | I89: =$C89*$D89*(1+$E89) -> 72016 | J89: =I89*70% -> 50411.2 | K89: =I89-J89 -> 21604.8
A90: 46301 | B90: TX-100088 | C90: 6 | D90: 10715 | E90: 0.07 | F90: 5 | G90: 6 | H90: =DATE(YEAR($A90),MONTH($A90),1) -> 46296 | I90: =$C90*$D90*(1+$E90) -> 68790.3 | J90: =I90*70% -> 48153.21 | K90: =I90-J90 -> 20637.09
A91: 46061 | B91: TX-100089 | C91: 10 | D91: 5065 | E91: 0.12 | F91: 4 | G91: 4 | H91: =DATE(YEAR($A91),MONTH($A91),1) -> 46054 | I91: =$C91*$D91*(1+$E91) -> 56728 | J91: =I91*70% -> 39709.6 | K91: =I91-J91 -> 17018.4
A92: 46158 | B92: TX-100090 | C92: 11 | D92: 24659 | E92: 0.04 | F92: 4 | G92: 1 | H92: =DATE(YEAR($A92),MONTH($A92),1) -> 46143 | I92: =$C92*$D92*(1+$E92) -> 282098.96 | J92: =I92*70% -> 197469.27 | K92: =I92-J92 -> 84629.688
A93: 46132 | B93: TX-100091 | C93: 10 | D93: 25538 | F93: 2 | G93: 3 | H93: =DATE(YEAR($A93),MONTH($A93),1) -> 46113 | I93: =$C93*$D93*(1+$E93) -> 255380 | J93: =I93*70% -> 178766 | K93: =I93-J93 -> 76614
A94: 46316 | B94: TX-100092 | C94: 12 | D94: 7030 | E94: 0.15 | F94: 4 | G94: 8 | H94: =DATE(YEAR($A94),MONTH($A94),1) -> 46296 | I94: =$C94*$D94*(1+$E94) -> 97014 | J94: =I94*70% -> 67909.8 | K94: =I94-J94 -> 29104.2
A95: 46303 | B95: TX-100093 | C95: 12 | D95: 5310 | F95: 1 | G95: 6 | H95: =DATE(YEAR($A95),MONTH($A95),1) -> 46296 | I95: =$C95*$D95*(1+$E95) -> 63720 | J95: =I95*70% -> 44604 | K95: =I95-J95 -> 19116
A96: 46265 | B96: TX-100094 | C96: 5 | D96: 26630 | F96: 3 | G96: 7 | H96: =DATE(YEAR($A96),MONTH($A96),1) -> 46235 | I96: =$C96*$D96*(1+$E96) -> 133150 | J96: =I96*70% -> 93205 | K96: =I96-J96 -> 39945
A97: 46229 | B97: TX-100095 | C97: 11 | D97: 3634 | E97: 0.07 | F97: 2 | G97: 4 | H97: =DATE(YEAR($A97),MONTH($A97),1) -> 46204 | I97: =$C97*$D97*(1+$E97) -> 42772.18 | J97: =I97*70% -> 29940.526 | K97: =I97-J97 -> 12831.654
A98: 46126 | B98: TX-100096 | C98: 3 | D98: 1899 | E98: 0.11 | F98: 4 | G98: 7 | H98: =DATE(YEAR($A98),MONTH($A98),1) -> 46113 | I98: =$C98*$D98*(1+$E98) -> 6323.67 | J98: =I98*70% -> 4426.569 | K98: =I98-J98 -> 1897.101
A99: 46086 | B99: TX-100097 | C99: 3 | D99: 32930 | E99: 0.1 | F99: 4 | G99: 7 | H99: =DATE(YEAR($A99),MONTH($A99),1) -> 46082 | I99: =$C99*$D99*(1+$E99) -> 108669 | J99: =I99*70% -> 76068.3 | K99: =I99-J99 -> 32600.7
A100: 46135 | B100: TX-100098 | C100: 2 | D100: 22114 | E100: 0.02 | F100: 1 | G100: 3 | H100: =DATE(YEAR($A100),MONTH($A100),1) -> 46113 | I100: =$C100*$D100*(1+$E100) -> 45112.56 | J100: =I100*70% -> 31578.792 | K100: =I100-J100 -> 13533.768
...

Sheet Dim Clientes
A1: ID_Cliente | B1: Cliente
A2: 1 | B2: Cliente 1
A3: 2 | B3: Cliente 2
A4: 3 | B4: Cliente 3
A5: 4 | B5: Cliente 4
A6: 5 | B6: Cliente 5

Sheet Dim Productos
A1: ID_Producto | B1: Producto
A2: 1 | B2: Producto 1
A3: 2 | B3: Producto 2
A4: 3 | B4: Producto 3
A5: 4 | B5: Producto 4
A6: 5 | B6: Producto 5
A7: 6 | B7: Producto 6
A8: 7 | B8: Producto 7
A9: 8 | B9: Producto 8

Sheet Dim Calendario
A1: Fecha | B1: Año | C1: Mes_Nro | D1: Mes | E1: Trimestre
A2: 46023 | B2: 2026 | C2: 1 | D2: ene | E2: T1
A3: 46024 | B3: 2026 | C3: 1 | D3: ene | E3: T1
A4: 46025 | B4: 2026 | C4: 1 | D4: ene | E4: T1
A5: 46026 | B5: 2026 | C5: 1 | D5: ene | E5: T1
A6: 46027 | B6: 2026 | C6: 1 | D6: ene | E6: T1
A7: 46028 | B7: 2026 | C7: 1 | D7: ene | E7: T1
A8: 46029 | B8: 2026 | C8: 1 | D8: ene | E8: T1
A9: 46030 | B9: 2026 | C9: 1 | D9: ene | E9: T1
A10: 46031 | B10: 2026 | C10: 1 | D10: ene | E10: T1
A11: 46032 | B11: 2026 | C11: 1 | D11: ene | E11: T1
A12: 46033 | B12: 2026 | C12: 1 | D12: ene | E12: T1
A13: 46034 | B13: 2026 | C13: 1 | D13: ene | E13: T1
... A366: 46387 | B366: 2026 | C366: 12 | D366: dic | E366: T4

Sheet Modelo Estrella
A1: Modelo en Estrella — Diseño Relacional
A5: DIM: Tbl_Clientes | D5: FACT: Ventas_Limpias | G5: DIM: Tbl_Productos
A6: PK | B6: ID_Cliente | D6: PK | E6: ID_Transaccion | G6: PK | H6: ID_Producto
A7: Atributo | B7: Cliente | D7: FK | E7: ID_Cliente | G7: Atributo | H7: Producto
D8: FK | E8: ID_Producto
D9: FK | E9: Fecha_Operacion
D12: DIM: Tbl_Calendario
D13: PK | E13: Fecha
D14: Atributo | E14: Año
D15: Atributo | E15: Mes
D16: Atributo | E16: Trimestre
A19: Relación | B19: Cardinalidad | C19: Dirección de filtro
A20: Tbl_Clientes[ID_Cliente] → Ventas_Limpias[ID_Cliente] | B20: 1:N | C20: Dimensión → Hechos
A21: Tbl_Productos[ID_Producto] → Ventas_Limpias[ID_Producto] | B21: 1:N | C21: Dimensión → Hechos
A22: Tbl_Calendario[Fecha] → Ventas_Limpias[Fecha_Operacion] | B22: 1:N | C22: Dimensión → Hechos

Sheet Código M y DAX
A1: Código documentado — Power Query M y DAX
A3: Consulta M: Ventas_Limpias
A4: let
A5: // ETL local sobre la tabla de ventas del libro
A6: Origen = Excel.CurrentWorkbook(){[Name="Tbl_Dataset"]}[Content],
A7: TiposCorregidos = Table.TransformColumnTypes(Origen, {{"Fecha_Operacion", type date}, {"ID_Transaccion", type text}, {"Bultos", Int64.Type}, {"Precio_Mayorista", Currency.Type}, {"Impuesto_Interno", Percentage.Type}, {"ID_Cliente", Int64.Type}, {"ID_Producto", Int64.Type}, {"Mes_Operacion", type text}, {"Venta_Total", Currency.Type}}),
A8: SinNulos = Table.SelectRows(TiposCorregidos, each [ID_Transaccion] <> null and [Venta_Total] <> null),
A9: VentasFiltradas = Table.SelectRows(SinNulos, each [Bultos] > 0 and [Venta_Total] > 0)
A10: in
A11: VentasFiltradas
A14: Medidas DAX optimizadas
A15: Medida | B15: Código DAX
A16: Total Ventas | B16: Total Ventas := SUM(Ventas_Limpias[Venta_Total])
A17: Costo Estimado | B17: Costo Estimado := SUM(Ventas_Limpias[Costo_Estimado])
A18: Margen Neto | B18: Margen Neto := VAR Ventas = [Total Ventas] VAR Costos = [Costo Estimado] RETURN Ventas - Costos
A19: Margen Neto % | B19: Margen Neto % := VAR Ventas = [Total Ventas] VAR Margen = [Margen Neto] RETURN DIVIDE(Margen, Ventas, 0)
A20: Ticket Promedio | B20: Ticket Promedio := VAR Ventas = [Total Ventas] VAR Operaciones = DISTINCTCOUNT(Ventas_Limpias[ID_Transaccion]) RETURN DIVIDE(Ventas, Operaciones, 0)
A23: Activación final en Excel
A24: 1 | B24: Datos → Obtener datos → Consulta en blanco → Editor avanzado: pegar el bloque M.
A25: 2 | B25: Cerrar y cargar en… → Solo crear conexión → Agregar estos datos al Modelo de Datos.
A26: 3 | B26: Power Pivot → Administrar → Vista de diagrama: crear las tres relaciones 1:N documentadas.
A27: 4 | B27: Crear las medidas usando el código DAX de esta hoja.
A28: 5 | B28: Guardar como PreEntrega_ModeloBI_PereyraNatalia.xlsx o .xlsb.

Sheet Estadística Descriptiva
A1: Estadística descriptiva — Venta Total
A3: Métrica | B3: Resultado
A4: Cantidad | B4: =COUNT('Dataset Principal'!I2:I5001) -> 5000
A5: Media | B5: =AVERAGE('Dataset Principal'!I2:I5001) -> 126590.96
A6: Mediana | B6: =MEDIAN('Dataset Principal'!I2:I5001) -> 99448.12
A7: Desvío estándar | B7: =_xlfn.STDEV.S('Dataset Principal'!I2:I5001) -> 99995.514
A8: Mínimo | B8: =MIN('Dataset Principal'!I2:I5001) -> 1619
A9: Máximo | B9: =MAX('Dataset Principal'!I2:I5001) -> 474354
A10: Rango | B10: =B9-B8 -> 472735
A11: Suma | B11: =SUM('Dataset Principal'!I2:I5001) -> 6.3295482e+08
A13: Lectura ejecutiva
A14: La mediana es inferior a la media, señal de operaciones grandes que elevan el promedio.
A15: El rango refleja una dispersión amplia en el importe por transacción.

Sheet Tabla dinámica del escenario
A1: $B$12:$D$12 por | B1: (Todas)
A3: Etiquetas de fila | B3: $G$12
A4: Base | B4: 1.8988645e+08
A5: Optimista | B5: 2.6805637e+08
A6: Pesimista | B6: 1.2247676e+08

Sheet Resumen de Escenarios
A1: Resumen de Escenarios y Objetivo
A3: Supuesto base | B3: Valor
A4: Unidades / bultos | B4: 32873
A5: Precio unitario promedio | B5: =SUM('Dataset Principal'!I2:I5001)/B4 -> 19254.55
A6: Costo unitario base | B6: =B5*70% -> 13478.185
A7: Beneficio objetivo | B7: 5000000
A8: Unidades requeridas | B8: =B7/(B5-B6) -> 865.59627
A11: Escenario | B11: Factor precio | C11: Factor costo | D11: Factor demanda | E11: Ventas | F11: Costos | G11: Beneficio
A12: Pesimista | B12: 0.95 | C12: 1.05 | D12: 0.9 | E12: =$B$4*D12*$B$5*B12 -> 5.4117637e+08 | F12: =$B$4*D12*$B$6*C12 -> 4.1869961e+08 | G12: =E12-F12 -> 1.2247676e+08
A13: Base | B13: 1 | C13: 1 | D13: 1 | E13: =$B$4*D13*$B$5*B13 -> 6.3295482e+08 | F13: =$B$4*D13*$B$6*C13 -> 4.4306838e+08 | G13: =E13-F13 -> 1.8988645e+08
A14: Optimista | B14: 1.05 | C14: 0.95 | D14: 1.1 | E14: =$B$4*D14*$B$5*B14 -> 7.3106282e+08 | F14: =$B$4*D14*$B$6*C14 -> 4.6300645e+08 | G14: =E14-F14 -> 2.6805637e+08
A17: Buscar objetivo equivalente: cambiar unidades hasta que Beneficio alcance $5.000.000.
A19: Búsqueda de objetivo | B19: Valor
A20: Unidades a calcular | B20: 865.59627
A21: Beneficio calculado | B21: =B20*($B$5-$B$6) -> 5000000
A22: Beneficio objetivo | B22: 5000000

Sheet Datos Dashboard
A1: Mes | B1: Producto | C1: Cliente | D1: Venta_Total | E1: Costo_Estimado | F1: Margen_Neto | G1: Bultos | H1: Visible
A2: 2026-08 | B2: Producto 1 | C2: Cliente 2 | D2: 18994.56 | E2: 13296.192 | F2: 5698.368 | G2: 6 | H2: =SUBTOTAL(103,A2) -> 1
A3: 2026-05 | B3: Producto 2 | C3: Cliente 4 | D3: 69563.7 | E3: 48694.59 | F3: 20869.11 | G3: 5 | H3: =SUBTOTAL(103,A3) -> 1
A4: 2026-02 | B4: Producto 3 | C4: Cliente 4 | D4: 23411.7 | E4: 16388.19 | F4: 7023.51 | G4: 2 | H4: =SUBTOTAL(103,A4) -> 1
A5: 2026-04 | B5: Producto 4 | C5: Cliente 4 | D5: 20355.75 | E5: 14249.025 | F5: 6106.725 | G5: 9 | H5: =SUBTOTAL(103,A5) -> 1
A6: 2026-06 | B6: Producto 5 | C6: Cliente 5 | D6: 82318.68 | E6: 57623.076 | F6: 24695.604 | G6: 3 | H6: =SUBTOTAL(103,A6) -> 1
A7: 2026-12 | B7: Producto 6 | C7: Cliente 2 | D7: 298089.2 | E7: 208662.44 | F7: 89426.76 | G7: 8 | H7: =SUBTOTAL(103,A7) -> 1
A8: 2026-11 | B8: Producto 5 | C8: Cliente 1 | D8: 142264.72 | E8: 99585.304 | F8: 42679.416 | G8: 4 | H8: =SUBTOTAL(103,A8) -> 1
A9: 2026-08 | B9: Producto 5 | C9: Cliente 5 | D9: 34644 | E9: 24250.8 | F9: 10393.2 | G9: 6 | H9: =SUBTOTAL(103,A9) -> 1
A10: 2026-12 | B10: Producto 6 | C10: Cliente 1 | D10: 239679 | E10: 167775.3 | F10: 71903.7 | G10: 11 | H10: =SUBTOTAL(103,A10) -> 1
A11: 2026-09 | B11: Producto 2 | C11: Cliente 5 | D11: 34543.2 | E11: 24180.24 | F11: 10362.96 | G11: 1 | H11: =SUBTOTAL(103,A11) -> 1
A12: 2026-05 | B12: Producto 5 | C12: Cliente 5 | D12: 94705 | E12: 66293.5 | F12: 28411.5 | G12: 5 | H12: =SUBTOTAL(103,A12) -> 1
A13: 2026-09 | B13: Producto 7 | C13: Cliente 1 | D13: 31358.35 | E13: 21950.845 | F13: 9407.505 | G13: 5 | H13: =SUBTOTAL(103,A13) -> 1
... A5001: 2026-03 | B5001: Producto 5 | C5001: Cliente 4 | D5001: 262317 | E5001: 183621.9 | F5001: 78695.1 | G5001: 11 | H5001: =SUBTOTAL(103,A5001) -> 1

Sheet Dashboard Final
A1: Dashboard Comercial 2026 | Z1: Mes | AA1: Ventas | AB1: Costo | AC1: Margen | AD1: Clave Pivot | AG1: Producto | AH1: Ventas | AJ1: Cliente | AK1: Ventas | AZ1: Mes | BA1: Producto | BB1: Cliente | BC1: Venta_Total | BD1: Costo_Estimado | BE1: Margen_Neto | BF1: Bultos
Z2: 46023 | AA2: =SUMIFS(tblDashFiltro[Venta_Total],tblDashFiltro[Mes],$AD2,tblDashFiltro[Visible],1) -> 51147001 | AB2: =SUMIFS(tblDashFiltro[Costo_Estimado],tblDashFiltro[Mes],$AD2,tblDashFiltro[Visible],1) -> 35802901 | AC2: =SUMIFS(tblDashFiltro[Margen_Neto],tblDashFiltro[Mes],$AD2,tblDashFiltro[Visible],1) -> 15344100 | AD2: 2026-01 | AG2: Producto 1 | AH2: =SUMIFS(tblDashFiltro[Venta_Total],tblDashFiltro[Producto],AG2,tblDashFiltro[Visible],1) -> 80861486 | AJ2: Cliente 1 | AK2: =SUMIFS(tblDashFiltro[Venta_Total],tblDashFiltro[Cliente],AJ2,tblDashFiltro[Visible],1) -> 1.2159391e+08 | AZ2: 2026-08 | BA2: Producto 1 | BB2: Cliente 2 | BC2: 18994.56 | BD2: 13296.192 | BE2: 5698.368 | BF2: 6
A3: ="Vista filtrada | "&SUBTOTAL(103,tblDashFiltro[Mes])&" operaciones | "&COUNTIF($AA$2:$AA$13,">0")&IF(COUNTIF($AA$2:$AA$13,">0")=1," mes | "," meses | ")&COUNTIF($AH$2:$AH$9,">0")&IF(COUNTIF($AH$2:$AH$9,">0")=1," producto | "," productos | ")&COUNTIF($AK$2:$AK$6,">0")&IF(COUNTIF($AK$2:$AK$6,">0")=1," cliente"," clientes") -> Vista filtrada | 5000 operaciones | 12 meses | 8 productos | 5 clientes | Z3: 46054 | AA3: =SUMIFS(tblDashFiltro[Venta_Total],tblDashFiltro[Mes],$AD3,tblDashFiltro[Visible],1) -> 55597128 | AB3: =SUMIFS(tblDashFiltro[Costo_Estimado],tblDashFiltro[Mes],$AD3,tblDashFiltro[Visible],1) -> 38917989 | AC3: =SUMIFS(tblDashFiltro[Margen_Neto],tblDashFiltro[Mes],$AD3,tblDashFiltro[Visible],1) -> 16679138 | AD3: 2026-02 | AG3: Producto 2 | AH3: =SUMIFS(tblDashFiltro[Venta_Total],tblDashFiltro[Producto],AG3,tblDashFiltro[Visible],1) -> 76452491 | AJ3: Cliente 2 | AK3: =SUMIFS(tblDashFiltro[Venta_Total],tblDashFiltro[Cliente],AJ3,tblDashFiltro[Visible],1) -> 1.3258341e+08 | AZ3: 2026-05 | BA3: Producto 2 | BB3: Cliente 4 | BC3: 69563.7 | BD3: 48694.59 | BE3: 20869.11 | BF3: 5
Z4: 46082 | AA4: =SUMIFS(tblDashFiltro[Venta_Total],tblDashFiltro[Mes],$AD4,tblDashFiltro[Visible],1) -> 49850424 | AB4: =SUMIFS(tblDashFiltro[Costo_Estimado],tblDashFiltro[Mes],$AD4,tblDashFiltro[Visible],1) -> 34895297 | AC4: =SUMIFS(tblDashFiltro[Margen_Neto],tblDashFiltro[Mes],$AD4,tblDashFiltro[Visible],1) -> 14955127 | AD4: 2026-03 | AG4: Producto 3 | AH4: =SUMIFS(tblDashFiltro[Venta_Total],tblDashFiltro[Producto],AG4,tblDashFiltro[Visible],1) -> 77873096 | AJ4: Cliente 3 | AK4: =SUMIFS(tblDashFiltro[Venta_Total],tblDashFiltro[Cliente],AJ4,tblDashFiltro[Visible],1) -> 1.2716917e+08 | AZ4: 2026-02 | BA4: Producto 3 | BB4: Cliente 4 | BC4: 23411.7 | BD4: 16388.19 | BE4: 7023.51 | BF4: 2
A5: VENTAS TOTALES | F5: MARGEN NETO % | K5: CRECIMIENTO YoY | Z5: 46113 | AA5: =SUMIFS(tblDashFiltro[Venta_Total],tblDashFiltro[Mes],$AD5,tblDashFiltro[Visible],1) -> 50017999 | AB5: =SUMIFS(tblDashFiltro[Costo_Estimado],tblDashFiltro[Mes],$AD5,tblDashFiltro[Visible],1) -> 35012600 | AC5: =SUMIFS(tblDashFiltro[Margen_Neto],tblDashFiltro[Mes],$AD5,tblDashFiltro[Visible],1) -> 15005400 | AD5: 2026-04 | AG5: Producto 4 | AH5: =SUMIFS(tblDashFiltro[Venta_Total],tblDashFiltro[Producto],AG5,tblDashFiltro[Visible],1) -> 77674840 | AJ5: Cliente 4 | AK5: =SUMIFS(tblDashFiltro[Venta_Total],tblDashFiltro[Cliente],AJ5,tblDashFiltro[Visible],1) -> 1.2740488e+08 | AZ5: 2026-04 | BA5: Producto 4 | BB5: Cliente 4 | BC5: 20355.75 | BD5: 14249.025 | BE5: 6106.725 | BF5: 9
A6: =SUBTOTAL(109,tblDashFiltro[Venta_Total]) -> 6.3295482e+08 | F6: =IFERROR(SUBTOTAL(109,tblDashFiltro[Margen_Neto])/SUBTOTAL(109,tblDashFiltro[Venta_Total]),0) -> 0.3 | K6: N/D | Z6: 46143 | AA6: =SUMIFS(tblDashFiltro[Venta_Total],tblDashFiltro[Mes],$AD6,tblDashFiltro[Visible],1) -> 53661071 | AB6: =SUMIFS(tblDashFiltro[Costo_Estimado],tblDashFiltro[Mes],$AD6,tblDashFiltro[Visible],1) -> 37562750 | AC6: =SUMIFS(tblDashFiltro[Margen_Neto],tblDashFiltro[Mes],$AD6,tblDashFiltro[Visible],1) -> 16098321 | AD6: 2026-05 | AG6: Producto 5 | AH6: =SUMIFS(tblDashFiltro[Venta_Total],tblDashFiltro[Producto],AG6,tblDashFiltro[Visible],1) -> 77252117 | AJ6: Cliente 5 | AK6: =SUMIFS(tblDashFiltro[Venta_Total],tblDashFiltro[Cliente],AJ6,tblDashFiltro[Visible],1) -> 1.2420345e+08 | AZ6: 2026-06 | BA6: Producto 5 | BB6: Cliente 5 | BC6: 82318.68 | BD6: 57623.076 | BE6: 24695.604 | BF6: 3
Z7: 46174 | AA7: =SUMIFS(tblDashFiltro[Venta_Total],tblDashFiltro[Mes],$AD7,tblDashFiltro[Visible],1) -> 50613744 | AB7: =SUMIFS(tblDashFiltro[Costo_Estimado],tblDashFiltro[Mes],$AD7,tblDashFiltro[Visible],1) -> 35429621 | AC7: =SUMIFS(tblDashFiltro[Margen_Neto],tblDashFiltro[Mes],$AD7,tblDashFiltro[Visible],1) -> 15184123 | AD7: 2026-06 | AG7: Producto 6 | AH7: =SUMIFS(tblDashFiltro[Venta_Total],tblDashFiltro[Producto],AG7,tblDashFiltro[Visible],1) -> 81787539 | AZ7: 2026-12 | BA7: Producto 6 | BB7: Cliente 2 | BC7: 298089.2 | BD7: 208662.44 | BE7: 89426.76 | BF7: 8
Z8: 46204 | AA8: =SUMIFS(tblDashFiltro[Venta_Total],tblDashFiltro[Mes],$AD8,tblDashFiltro[Visible],1) -> 54996502 | AB8: =SUMIFS(tblDashFiltro[Costo_Estimado],tblDashFiltro[Mes],$AD8,tblDashFiltro[Visible],1) -> 38497552 | AC8: =SUMIFS(tblDashFiltro[Margen_Neto],tblDashFiltro[Mes],$AD8,tblDashFiltro[Visible],1) -> 16498951 | AD8: 2026-07 | AG8: Producto 7 | AH8: =SUMIFS(tblDashFiltro[Venta_Total],tblDashFiltro[Producto],AG8,tblDashFiltro[Visible],1) -> 82404026 | AZ8: 2026-11 | BA8: Producto 5 | BB8: Cliente 1 | BC8: 142264.72 | BD8: 99585.304 | BE8: 42679.416 | BF8: 4
Z9: 46235 | AA9: =SUMIFS(tblDashFiltro[Venta_Total],tblDashFiltro[Mes],$AD9,tblDashFiltro[Visible],1) -> 56742403 | AB9: =SUMIFS(tblDashFiltro[Costo_Estimado],tblDashFiltro[Mes],$AD9,tblDashFiltro[Visible],1) -> 39719682 | AC9: =SUMIFS(tblDashFiltro[Margen_Neto],tblDashFiltro[Mes],$AD9,tblDashFiltro[Visible],1) -> 17022721 | AD9: 2026-08 | AG9: Producto 8 | AH9: =SUMIFS(tblDashFiltro[Venta_Total],tblDashFiltro[Producto],AG9,tblDashFiltro[Visible],1) -> 78649226 | AZ9: 2026-08 | BA9: Producto 5 | BB9: Cliente 5 | BC9: 34644 | BD9: 24250.8 | BE9: 10393.2 | BF9: 6
Z10: 46266 | AA10: =SUMIFS(tblDashFiltro[Venta_Total],tblDashFiltro[Mes],$AD10,tblDashFiltro[Visible],1) -> 49489162 | AB10: =SUMIFS(tblDashFiltro[Costo_Estimado],tblDashFiltro[Mes],$AD10,tblDashFiltro[Visible],1) -> 34642413 | AC10: =SUMIFS(tblDashFiltro[Margen_Neto],tblDashFiltro[Mes],$AD10,tblDashFiltro[Visible],1) -> 14846749 | AD10: 2026-09 | AZ10: 2026-12 | BA10: Producto 6 | BB10: Cliente 1 | BC10: 239679 | BD10: 167775.3 | BE10: 71903.7 | BF10: 11
Z11: 46296 | AA11: =SUMIFS(tblDashFiltro[Venta_Total],tblDashFiltro[Mes],$AD11,tblDashFiltro[Visible],1) -> 54656574 | AB11: =SUMIFS(tblDashFiltro[Costo_Estimado],tblDashFiltro[Mes],$AD11,tblDashFiltro[Visible],1) -> 38259602 | AC11: =SUMIFS(tblDashFiltro[Margen_Neto],tblDashFiltro[Mes],$AD11,tblDashFiltro[Visible],1) -> 16396972 | AD11: 2026-10 | AZ11: 2026-09 | BA11: Producto 2 | BB11: Cliente 5 | BC11: 34543.2 | BD11: 24180.24 | BE11: 10362.96 | BF11: 1
Z12: 46327 | AA12: =SUMIFS(tblDashFiltro[Venta_Total],tblDashFiltro[Mes],$AD12,tblDashFiltro[Visible],1) -> 51519994 | AB12: =SUMIFS(tblDashFiltro[Costo_Estimado],tblDashFiltro[Mes],$AD12,tblDashFiltro[Visible],1) -> 36063996 | AC12: =SUMIFS(tblDashFiltro[Margen_Neto],tblDashFiltro[Mes],$AD12,tblDashFiltro[Visible],1) -> 15455998 | AD12: 2026-11 | AZ12: 2026-05 | BA12: Producto 5 | BB12: Cliente 5 | BC12: 94705 | BD12: 66293.5 | BE12: 28411.5 | BF12: 5
Z13: 46357 | AA13: =SUMIFS(tblDashFiltro[Venta_Total],tblDashFiltro[Mes],$AD13,tblDashFiltro[Visible],1) -> 53359350 | AB13: =SUMIFS(tblDashFiltro[Costo_Estimado],tblDashFiltro[Mes],$AD13,tblDashFiltro[Visible],1) -> 37351545 | AC13: =SUMIFS(tblDashFiltro[Margen_Neto],tblDashFiltro[Mes],$AD13,tblDashFiltro[Visible],1) -> 16007805 | AD13: 2026-12 | AZ13: 2026-09 | BA13: Producto 7 | BB13: Cliente 1 | BC13: 31358.35 | BD13: 21950.845 | BE13: 9407.505 | BF13: 5
AZ14: 2026-07 | BA14: Producto 2 | BB14: Cliente 4 | BC14: 273593.6 | BD14: 191515.52 | BE14: 82078.08 | BF14: 8
AZ15: 2026-09 | BA15: Producto 1 | BB15: Cliente 5 | BC15: 266133 | BD15: 186293.1 | BE15: 79839.9 | BF15: 10
AZ16: 2026-06 | BA16: Producto 1 | BB16: Cliente 2 | BC16: 9471.88 | BD16: 6630.316 | BE16: 2841.564 | BF16: 4
AZ17: 2026-10 | BA17: Producto 4 | BB17: Cliente 5 | BC17: 31790 | BD17: 22253 | BE17: 9537 | BF17: 10
AZ18: 2026-03 | BA18: Producto 3 | BB18: Cliente 4 | BC18: 127525.44 | BD18: 89267.808 | BE18: 38257.632 | BF18: 7
AZ19: 2026-10 | BA19: Producto 3 | BB19: Cliente 5 | BC19: 55750.86 | BD19: 39025.602 | BE19: 16725.258 | BF19: 3
AZ20: 2026-02 | BA20: Producto 8 | BB20: Cliente 3 | BC20: 30855.24 | BD20: 21598.668 | BE20: 9256.572 | BF20: 2
AZ21: 2026-05 | BA21: Producto 7 | BB21: Cliente 3 | BC21: 5564.45 | BD21: 3895.115 | BE21: 1669.335 | BF21: 1
AZ22: 2026-04 | BA22: Producto 1 | BB22: Cliente 2 | BC22: 178981 | BD22: 125286.7 | BE22: 53694.3 | BF22: 10
AZ23: 2026-10 | BA23: Producto 1 | BB23: Cliente 1 | BC23: 13092 | BD23: 9164.4 | BE23: 3927.6 | BF23: 1
AZ24: 2026-10 | BA24: Producto 8 | BB24: Cliente 3 | BC24: 263680 | BD24: 184576 | BE24: 79104 | BF24: 10
AZ25: 2026-08 | BA25: Producto 4 | BB25: Cliente 4 | BC25: 213850 | BD25: 149695 | BE25: 64155 | BF25: 10
A26: 3 CONCLUSIONES BASADAS EN LOS DATOS | I26: ABOGADO DEL DIABLO — REVISIÓN CHATGPT | AZ26: 2026-07 | BA26: Producto 3 | BB26: Cliente 2 | BC26: 116940 | BD26: 81858 | BE26: 35082 | BF26: 5
A27: =IF(SUM($AA$2:$AA$13)=0,"1. No hay operaciones para la combinación seleccionada.","1. "&TEXT(INDEX($Z$2:$Z$13,MATCH(MAX($AA$2:$AA$13),$AA$2:$AA$13,0)),"mmmm")&" lidera con $"&ROUND(MAX($AA$2:$AA$13)/1000000,2)&" M ("&ROUND(100*MAX($AA$2:$AA$13)/SUM($AA$2:$AA$13),1)&"%) de las ventas fechadas visibles.") -> 1. agosto lidera con $56,74 M (9%) de las ventas fechadas visibles. | I27: =IF(SUBTOTAL(103,tblDashFiltro[Mes])<30,"Objeción 1 → La selección contiene solo "&SUBTOTAL(103,tblDashFiltro[Mes])&" operaciones; el mes líder puede ser sensible a pocos casos.","Objeción 1 → Un solo año no permite separar estacionalidad de variación aleatoria; no debe asumirse que el mes líder se repetirá.") -> Objeción 1 → Un solo año no permite separar estacionalidad de variación aleatoria; no debe asumirse que el mes líder se repetirá. | AZ27: 2026-04 | BA27: Producto 6 | BB27: Cliente 1 | BC27: 32533.2 | BD27: 22773.24 | BE27: 9759.96 | BF27: 12
AZ28: 2026-03 | BA28: Producto 2 | BB28: Cliente 2 | BC28: 26134 | BD28: 18293.8 | BE28: 7840.2 | BF28: 2
AZ29: 2026-04 | BA29: Producto 7 | BB29: Cliente 4 | BC29: 188504 | BD29: 131952.8 | BE29: 56551.2 | BF29: 8
AZ30: 2026-09 | BA30: Producto 8 | BB30: Cliente 4 | BC30: 285763.5 | BD30: 200034.45 | BE30: 85729.05 | BF30: 10
A31: =IF(SUM($AH$2:$AH$9)=0,"2. No hay productos con ventas para la selección.","2. "&INDEX($AG$2:$AG$9,MATCH(MAX($AH$2:$AH$9),$AH$2:$AH$9,0))&" lidera con $"&ROUND(MAX($AH$2:$AH$9)/1000000,2)&" M ("&ROUND(100*MAX($AH$2:$AH$9)/SUM($AH$2:$AH$9),1)&"%) de la selección.") -> 2. Producto 7 lidera con $82,4 M (13%) de la selección. | I31: ="Objeción 2 → El liderazgo de "&IFERROR(INDEX($AG$2:$AG$9,MATCH(MAX($AH$2:$AH$9),$AH$2:$AH$9,0)),"un producto")&" es por ventas, no por rentabilidad: el costo está modelado como 70% para todos." -> Objeción 2 → El liderazgo de Producto 7 es por ventas, no por rentabilidad: el costo está modelado como 70% para todos. | AZ31: 2026-02 | BA31: Producto 6 | BB31: Cliente 2 | BC31: 249886.56 | BD31: 174920.59 | BE31: 74965.968 | BF31: 11
AZ32: 2026-02 | BA32: Producto 4 | BB32: Cliente 1 | BC32: 234001.2 | BD32: 163800.84 | BE32: 70200.36 | BF32: 12
AZ33: 2026-06 | BA33: Producto 2 | BB33: Cliente 4 | BC33: 26199.24 | BD33: 18339.468 | BE33: 7859.772 | BF33: 4
AZ34: 2026-11 | BA34: Producto 1 | BB34: Cliente 2 | BC34: 269434.88 | BD34: 188604.42 | BE34: 80830.464 | BF34: 11
A35: =IF(SUM($AK$2:$AK$6)=0,"3. No hay clientes con ventas para la selección.","3. "&INDEX($AJ$2:$AJ$6,MATCH(MAX($AK$2:$AK$6),$AK$2:$AK$6,0))&" concentra $"&ROUND(MAX($AK$2:$AK$6)/1000000,2)&" M ("&ROUND(100*MAX($AK$2:$AK$6)/SUM($AK$2:$AK$6),1)&"%) de la selección.") -> 3. Cliente 2 concentra $132,58 M (20,9%) de la selección. | I35: ="Objeción 3 → La concentración en "&IFERROR(INDEX($AJ$2:$AJ$6,MATCH(MAX($AK$2:$AK$6),$AK$2:$AK$6,0)),"un cliente")&" no captura región, canal ni solvencia; esas variables no existen en el modelo." -> Objeción 3 → La concentración en Cliente 2 no captura región, canal ni solvencia; esas variables no existen en el modelo. | AZ35: 2026-06 | BA35: Producto 4 | BB35: Cliente 5 | BC35: 110920 | BD35: 77644 | BE35: 33276 | BF35: 4
AZ36: 2026-04 | BA36: Producto 2 | BB36: Cliente 4 | BC36: 70944 | BD36: 49660.8 | BE36: 21283.2 | BF36: 6
AZ37: 2026-04 | BA37: Producto 1 | BB37: Cliente 3 | BC37: 67870.8 | BD37: 47509.56 | BE37: 20361.24 | BF37: 4
AZ38: 2026-12 | BA38: Producto 3 | BB38: Cliente 1 | BC38: 27124.9 | BD38: 18987.43 | BE38: 8137.47 | BF38: 1
AZ39: 2026-03 | BA39: Producto 5 | BB39: Cliente 3 | BC39: 27276.44 | BD39: 19093.508 | BE39: 8182.932 | BF39: 1
A40: Nota metodológica: 5.000 operaciones de 2026. El margen de 30,0% es modelado (costo estimado = 70% de ventas). YoY se mantiene como N/D porque no existe un año previo. Ambos gráficos, KPIs, resumen mensual y narrativa responden a Mes, Producto y Cliente; se usan estos filtros porque no existen Categoría ni Región. | AZ40: 2026-12 | BA40: Producto 8 | BB40: Cliente 5 | BC40: 64218 | BD40: 44952.6 | BE40: 19265.4 | BF40: 4
AZ41: 2026-01 | BA41: Producto 1 | BB41: Cliente 2 | BC41: 304283.1 | BD41: 212998.17 | BE41: 91284.93 | BF41: 11
AZ42: 2026-01 | BA42: Producto 6 | BB42: Cliente 4 | BC42: 210022.4 | BD42: 147015.68 | BE42: 63006.72 | BF42: 8
AZ43: 2026-05 | BA43: Producto 6 | BB43: Cliente 3 | BC43: 160650 | BD43: 112455 | BE43: 48195 | BF43: 9
A44: RESUMEN MENSUAL DINÁMICO | AZ44: 2026-06 | BA44: Producto 5 | BB44: Cliente 5 | BC44: 8348.55 | BD44: 5843.985 | BE44: 2504.565 | BF44: 1
A45: Mes | B45: Ventas | C45: Costo estimado | D45: Margen neto | AZ45: 2026-12 | BA45: Producto 8 | BB45: Cliente 1 | BC45: 35604.36 | BD45: 24923.052 | BE45: 10681.308 | BF45: 11
A46: 2026-01 | B46: =SUMIFS(tblDashFiltro[Venta_Total],tblDashFiltro[Mes],IF($A46="Sin fecha","undefined-undefined",$A46),tblDashFiltro[Visible],1) -> 51147001 | C46: =SUMIFS(tblDashFiltro[Costo_Estimado],tblDashFiltro[Mes],IF($A46="Sin fecha","undefined-undefined",$A46),tblDashFiltro[Visible],1) -> 35802901 | D46: =SUMIFS(tblDashFiltro[Margen_Neto],tblDashFiltro[Mes],IF($A46="Sin fecha","undefined-undefined",$A46),tblDashFiltro[Visible],1) -> 15344100 | AZ46: 2026-11 | BA46: Producto 4 | BB46: Cliente 5 | BC46: 15047 | BD46: 10532.9 | BE46: 4514.1 | BF46: 1
A47: 2026-02 | B47: =SUMIFS(tblDashFiltro[Venta_Total],tblDashFiltro[Mes],IF($A47="Sin fecha","undefined-undefined",$A47),tblDashFiltro[Visible],1) -> 55597128 | C47: =SUMIFS(tblDashFiltro[Costo_Estimado],tblDashFiltro[Mes],IF($A47="Sin fecha","undefined-undefined",$A47),tblDashFiltro[Visible],1) -> 38917989 | D47: =SUMIFS(tblDashFiltro[Margen_Neto],tblDashFiltro[Mes],IF($A47="Sin fecha","undefined-undefined",$A47),tblDashFiltro[Visible],1) -> 16679138 | AZ47: 2026-06 | BA47: Producto 1 | BB47: Cliente 1 | BC47: 46671.8 | BD47: 32670.26 | BE47: 14001.54 | BF47: 7
A48: 2026-03 | B48: =SUMIFS(tblDashFiltro[Venta_Total],tblDashFiltro[Mes],IF($A48="Sin fecha","undefined-undefined",$A48),tblDashFiltro[Visible],1) -> 49850424 | C48: =SUMIFS(tblDashFiltro[Costo_Estimado],tblDashFiltro[Mes],IF($A48="Sin fecha","undefined-undefined",$A48),tblDashFiltro[Visible],1) -> 34895297 | D48: =SUMIFS(tblDashFiltro[Margen_Neto],tblDashFiltro[Mes],IF($A48="Sin fecha","undefined-undefined",$A48),tblDashFiltro[Visible],1) -> 14955127 | AZ48: 2026-02 | BA48: Producto 2 | BB48: Cliente 2 | BC48: 64310.2 | BD48: 45017.14 | BE48: 19293.06 | BF48: 2
A49: 2026-04 | B49: =SUMIFS(tblDashFiltro[Venta_Total],tblDashFiltro[Mes],IF($A49="Sin fecha","undefined-undefined",$A49),tblDashFiltro[Visible],1) -> 50017999 | C49: =SUMIFS(tblDashFiltro[Costo_Estimado],tblDashFiltro[Mes],IF($A49="Sin fecha","undefined-undefined",$A49),tblDashFiltro[Visible],1) -> 35012600 | D49: =SUMIFS(tblDashFiltro[Margen_Neto],tblDashFiltro[Mes],IF($A49="Sin fecha","undefined-undefined",$A49),tblDashFiltro[Visible],1) -> 15005400 | AZ49: 2026-10 | BA49: Producto 7 | BB49: Cliente 1 | BC49: 119656.2 | BD49: 83759.34 | BE49: 35896.86 | BF49: 10
A50: 2026-05 | B50: =SUMIFS(tblDashFiltro[Venta_Total],tblDashFiltro[Mes],IF($A50="Sin fecha","undefined-undefined",$A50),tblDashFiltro[Visible],1) -> 53661071 | C50: =SUMIFS(tblDashFiltro[Costo_Estimado],tblDashFiltro[Mes],IF($A50="Sin fecha","undefined-undefined",$A50),tblDashFiltro[Visible],1) -> 37562750 | D50: =SUMIFS(tblDashFiltro[Margen_Neto],tblDashFiltro[Mes],IF($A50="Sin fecha","undefined-undefined",$A50),tblDashFiltro[Visible],1) -> 16098321 | AZ50: 2026-01 | BA50: Producto 3 | BB50: Cliente 4 | BC50: 237184.74 | BD50: 166029.32 | BE50: 71155.422 | BF50: 9
A51: 2026-06 | B51: =SUMIFS(tblDashFiltro[Venta_Total],tblDashFiltro[Mes],IF($A51="Sin fecha","undefined-undefined",$A51),tblDashFiltro[Visible],1) -> 50613744 | C51: =SUMIFS(tblDashFiltro[Costo_Estimado],tblDashFiltro[Mes],IF($A51="Sin fecha","undefined-undefined",$A51),tblDashFiltro[Visible],1) -> 35429621 | D51: =SUMIFS(tblDashFiltro[Margen_Neto],tblDashFiltro[Mes],IF($A51="Sin fecha","undefined-undefined",$A51),tblDashFiltro[Visible],1) -> 15184123 | AZ51: 2026-11 | BA51: Producto 3 | BB51: Cliente 3 | BC51: 115792.6 | BD51: 81054.82 | BE51: 34737.78 | BF51: 5
A52: 2026-07 | B52: =SUMIFS(tblDashFiltro[Venta_Total],tblDashFiltro[Mes],IF($A52="Sin fecha","undefined-undefined",$A52),tblDashFiltro[Visible],1) -> 54996502 | C52: =SUMIFS(tblDashFiltro[Costo_Estimado],tblDashFiltro[Mes],IF($A52="Sin fecha","undefined-undefined",$A52),tblDashFiltro[Visible],1) -> 38497552 | D52: =SUMIFS(tblDashFiltro[Margen_Neto],tblDashFiltro[Mes],IF($A52="Sin fecha","undefined-undefined",$A52),tblDashFiltro[Visible],1) -> 16498951 | AZ52: 2026-02 | BA52: Producto 6 | BB52: Cliente 5 | BC52: 50129.52 | BD52: 35090.664 | BE52: 15038.856 | BF52: 7
A53: 2026-08 | B53: =SUMIFS(tblDashFiltro[Venta_Total],tblDashFiltro[Mes],IF($A53="Sin fecha","undefined-undefined",$A53),tblDashFiltro[Visible],1) -> 56742403 | C53: =SUMIFS(tblDashFiltro[Costo_Estimado],tblDashFiltro[Mes],IF($A53="Sin fecha","undefined-undefined",$A53),tblDashFiltro[Visible],1) -> 39719682 | D53: =SUMIFS(tblDashFiltro[Margen_Neto],tblDashFiltro[Mes],IF($A53="Sin fecha","undefined-undefined",$A53),tblDashFiltro[Visible],1) -> 17022721 | AZ53: 2026-05 | BA53: Producto 3 | BB53: Cliente 2 | BC53: 227127.36 | BD53: 158989.15 | BE53: 68138.208 | BF53: 8
A54: 2026-09 | B54: =SUMIFS(tblDashFiltro[Venta_Total],tblDashFiltro[Mes],IF($A54="Sin fecha","undefined-undefined",$A54),tblDashFiltro[Visible],1) -> 49489162 | C54: =SUMIFS(tblDashFiltro[Costo_Estimado],tblDashFiltro[Mes],IF($A54="Sin fecha","undefined-undefined",$A54),tblDashFiltro[Visible],1) -> 34642413 | D54: =SUMIFS(tblDashFiltro[Margen_Neto],tblDashFiltro[Mes],IF($A54="Sin fecha","undefined-undefined",$A54),tblDashFiltro[Visible],1) -> 14846749 | AZ54: 2026-01 | BA54: Producto 8 | BB54: Cliente 2 | BC54: 115438.24 | BD54: 80806.768 | BE54: 34631.472 | BF54: 8
A55: 2026-10 | B55: =SUMIFS(tblDashFiltro[Venta_Total],tblDashFiltro[Mes],IF($A55="Sin fecha","undefined-undefined",$A55),tblDashFiltro[Visible],1) -> 54656574 | C55: =SUMIFS(tblDashFiltro[Costo_Estimado],tblDashFiltro[Mes],IF($A55="Sin fecha","undefined-undefined",$A55),tblDashFiltro[Visible],1) -> 38259602 | D55: =SUMIFS(tblDashFiltro[Margen_Neto],tblDashFiltro[Mes],IF($A55="Sin fecha","undefined-undefined",$A55),tblDashFiltro[Visible],1) -> 16396972 | AZ55: 2026-07 | BA55: Producto 5 | BB55: Cliente 3 | BC55: 116010.96 | BD55: 81207.672 | BE55: 34803.288 | BF55: 8
A56: 2026-11 | B56: =SUMIFS(tblDashFiltro[Venta_Total],tblDashFiltro[Mes],IF($A56="Sin fecha","undefined-undefined",$A56),tblDashFiltro[Visible],1) -> 51519994 | C56: =SUMIFS(tblDashFiltro[Costo_Estimado],tblDashFiltro[Mes],IF($A56="Sin fecha","undefined-undefined",$A56),tblDashFiltro[Visible],1) -> 36063996 | D56: =SUMIFS(tblDashFiltro[Margen_Neto],tblDashFiltro[Mes],IF($A56="Sin fecha","undefined-undefined",$A56),tblDashFiltro[Visible],1) -> 15455998 | AZ56: 2026-04 | BA56: Producto 1 | BB56: Cliente 5 | BC56: 7925.85 | BD56: 5548.095 | BE56: 2377.755 | BF56: 3
A57: 2026-12 | B57: =SUMIFS(tblDashFiltro[Venta_Total],tblDashFiltro[Mes],IF($A57="Sin fecha","undefined-undefined",$A57),tblDashFiltro[Visible],1) -> 53359350 | C57: =SUMIFS(tblDashFiltro[Costo_Estimado],tblDashFiltro[Mes],IF($A57="Sin fecha","undefined-undefined",$A57),tblDashFiltro[Visible],1) -> 37351545 | D57: =SUMIFS(tblDashFiltro[Margen_Neto],tblDashFiltro[Mes],IF($A57="Sin fecha","undefined-undefined",$A57),tblDashFiltro[Visible],1) -> 16007805 | AZ57: 2026-12 | BA57: Producto 2 | BB57: Cliente 4 | BC57: 246239.1 | BD57: 172367.37 | BE57: 73871.73 | BF57: 9
A58: Sin fecha | B58: =SUMIFS(tblDashFiltro[Venta_Total],tblDashFiltro[Mes],"Sin fecha",tblDashFiltro[Visible],1) -> 1303467.8 | C58: =SUMIFS(tblDashFiltro[Costo_Estimado],tblDashFiltro[Mes],"Sin fecha",tblDashFiltro[Visible],1) -> 912427.48 | D58: =SUMIFS(tblDashFiltro[Margen_Neto],tblDashFiltro[Mes],"Sin fecha",tblDashFiltro[Visible],1) -> 391040.35 | AZ58: 2026-04 | BA58: Producto 2 | BB58: Cliente 5 | BC58: 42316.56 | BD58: 29621.592 | BE58: 12694.968 | BF58: 2
AZ59: 2026-06 | BA59: Producto 4 | BB59: Cliente 4 | BC59: 163874.88 | BD59: 114712.42 | BE59: 49162.464 | BF59: 12
AZ60: 2026-01 | BA60: Producto 5 | BB60: Cliente 1 | BC60: 29184 | BD60: 20428.8 | BE60: 8755.2 | BF60: 6
AZ61: 2026-02 | BA61: Producto 6 | BB61: Cliente 1 | BC61: 71229.76 | BD61: 49860.832 | BE61: 21368.928 | BF61: 2
AZ62: 2026-05 | BA62: Producto 6 | BB62: Cliente 4 | BC62: 136693.98 | BD62: 95685.786 | BE62: 41008.194 | BF62: 9
AZ63: 2026-06 | BA63: Producto 1 | BB63: Cliente 1 | BC63: 67270.32 | BD63: 47089.224 | BE63: 20181.096 | BF63: 9
AZ64: 2026-03 | BA64: Producto 1 | BB64: Cliente 2 | BC64: 15344 | BD64: 10740.8 | BE64: 4603.2 | BF64: 1
AZ65: 2026-01 | BA65: Producto 2 | BB65: Cliente 5 | BC65: 233984.58 | BD65: 163789.21 | BE65: 70195.374 | BF65: 6
AZ66: 2026-10 | BA66: Producto 7 | BB66: Cliente 2 | BC66: 196160 | BD66: 137312 | BE66: 58848 | BF66: 8
AZ67: 2026-05 | BA67: Producto 5 | BB67: Cliente 2 | BC67: 233025.12 | BD67: 163117.58 | BE67: 69907.536 | BF67: 9
AZ68: 2026-09 | BA68: Producto 8 | BB68: Cliente 5 | BC68: 116272 | BD68: 81390.4 | BE68: 34881.6 | BF68: 10
AZ69: 2026-01 | BA69: Producto 7 | BB69: Cliente 5 | BC69: 28592 | BD69: 20014.4 | BE69: 8577.6 | BF69: 1
AZ70: 2026-01 | BA70: Producto 8 | BB70: Cliente 1 | BC70: 41227.2 | BD70: 28859.04 | BE70: 12368.16 | BF70: 5
... AZ5001: 2026-03 | BA5001: Producto 5 | BB5001: Cliente 4 | BC5001: 262317 | BD5001: 183621.9 | BE5001: 78695.1 | BF5001: 11
